Workbook

Sheet Dashboard
A1: Spark Lakehouse Lab - Progress Dashboard
A2: Instacart | PostgreSQL | RustFS | Apache Iceberg | Spark 4.x standalone. All numbers on this sheet are formulas; do not type over them.
A4: HOW TO USE
A5: Yellow cells are yours to edit: Status (dropdown), Started, Completed and Evidence / notes on each checklist tab.
A6: Status values: Not started, In progress, Blocked, Done, Skipped. Skipped items are excluded from % complete.
A7: Example: set Status = Done, Completed = 2026-11-03, Evidence = 'E-014, D-003' (experiment and defect IDs).
A8: Log every experiment on Experiments (prediction first), every data issue on Defects, every choice on Decisions.
A9: Grey italic rows on the log tabs are examples: overwrite or delete them. Suggested order: Setup, P1 (M0-M5), P3 and P2, P1 (M2, M6-M8), P4, P5.
A11: OVERALL PROGRESS
A12: Scope | B12: Detail | C12: Total | D12: Done | E12: In progress | F12: Blocked | G12: Not started | H12: Skipped | I12: % complete | J12: Next task
A13: All areas | B13: Setup + five projects | C13: =SUM(C17:C22) -> 498 | D13: =SUM(D17:D22) -> 0 | E13: =SUM(E17:E22) -> 0 | F13: =SUM(F17:F22) -> 0 | G13: =SUM(G17:G22) -> 498 | H13: =SUM(H17:H22) -> 0 | I13: =IFERROR(D13/(C13-H13),0) -> 0 | J13: =D13&" of "&(C13-H13)&" items complete" -> 0 of 498 items complete
A15: BY AREA
A16: Area | B16: Open this tab | C16: Total | D16: Done | E16: In progress | F16: Blocked | G16: Not started | H16: Skipped | I16: % complete | J16: Next task (first In progress, else first Not started)
A17: Setup and gates | B17: Setup and gates (open tab) | C17: =SUM(D17:H17) -> 47 | D17: =COUNTIF(Setup!$E$6:$E$600,"Done") -> 0 | E17: =COUNTIF(Setup!$E$6:$E$600,"In progress") -> 0 | F17: =COUNTIF(Setup!$E$6:$E$600,"Blocked") -> 0 | G17: =COUNTIF(Setup!$E$6:$E$600,"Not started") -> 47 | H17: =COUNTIF(Setup!$E$6:$E$600,"Skipped") -> 0 | I17: =IFERROR(D17/(C17-H17),0) -> 0 | J17: =IFERROR(INDEX(Setup!$C$6:$C$600,MATCH("In progress",Setup!$E$6:$E$600,0)),IFERROR(INDEX(Setup!$C$6:$C$600,MATCH("Not started",Setup!$E$6:$E$600,0)),"All items complete")) -> Gate A: find the Iceberg Spark runtime artifact that matches your Spark minor version (Scala 2.13) on Maven Central. If the Spark 4.2 runtime is missing, pin Spark to the newest 4.x that has one. Record in Environment and Decisions.
A18: Project 1 | B18: Project 1: Lakehouse medallion ETL | C18: =SUM(D18:H18) -> 113 | D18: =COUNTIF(P1_ETL!$E$6:$E$600,"Done") -> 0 | E18: =COUNTIF(P1_ETL!$E$6:$E$600,"In progress") -> 0 | F18: =COUNTIF(P1_ETL!$E$6:$E$600,"Blocked") -> 0 | G18: =COUNTIF(P1_ETL!$E$6:$E$600,"Not started") -> 113 | H18: =COUNTIF(P1_ETL!$E$6:$E$600,"Skipped") -> 0 | I18: =IFERROR(D18/(C18-H18),0) -> 0 | J18: =IFERROR(INDEX(P1_ETL!$C$6:$C$600,MATCH("In progress",P1_ETL!$E$6:$E$600,0)),IFERROR(INDEX(P1_ETL!$C$6:$C$600,MATCH("Not started",P1_ETL!$E$6:$E$600,0)),"All items complete")) -> Keep an untouched copy of the raw files in landing/raw_dump (everything must be reproducible from it).
A19: Project 2 | B19: Project 2: Joins, shuffles and skew | C19: =SUM(D19:H19) -> 91 | D19: =COUNTIF(P2_Joins!$E$6:$E$600,"Done") -> 0 | E19: =COUNTIF(P2_Joins!$E$6:$E$600,"In progress") -> 0 | F19: =COUNTIF(P2_Joins!$E$6:$E$600,"Blocked") -> 0 | G19: =COUNTIF(P2_Joins!$E$6:$E$600,"Not started") -> 91 | H19: =COUNTIF(P2_Joins!$E$6:$E$600,"Skipped") -> 0 | I19: =IFERROR(D19/(C19-H19),0) -> 0 | J19: =IFERROR(INDEX(P2_Joins!$C$6:$C$600,MATCH("In progress",P2_Joins!$E$6:$E$600,0)),IFERROR(INDEX(P2_Joins!$C$6:$C$600,MATCH("Not started",P2_Joins!$E$6:$E$600,0)),"All items complete")) -> Freeze the data version: record Iceberg snapshot ids of lines, orders, products, aisles, departments, users, stores, price book, payments, events.
A20: Project 3 | B20: Project 3: Catalyst and query planning | C20: =SUM(D20:H20) -> 79 | D20: =COUNTIF(P3_Planner!$E$6:$E$600,"Done") -> 0 | E20: =COUNTIF(P3_Planner!$E$6:$E$600,"In progress") -> 0 | F20: =COUNTIF(P3_Planner!$E$6:$E$600,"Blocked") -> 0 | G20: =COUNTIF(P3_Planner!$E$6:$E$600,"Not started") -> 79 | H20: =COUNTIF(P3_Planner!$E$6:$E$600,"Skipped") -> 0 | I20: =IFERROR(D20/(C20-H20),0) -> 0 | J20: =IFERROR(INDEX(P3_Planner!$C$6:$C$600,MATCH("In progress",P3_Planner!$E$6:$E$600,0)),IFERROR(INDEX(P3_Planner!$C$6:$C$600,MATCH("Not started",P3_Planner!$E$6:$E$600,0)),"All items complete")) -> Build lines/events variants: unsorted monthly-partitioned; sorted by product; z-ordered (department, hour); unpartitioned sorted; raw Parquet copy in landing.
A21: Project 4 | B21: Project 4: Executors, memory and I/O performance | C21: =SUM(D21:H21) -> 91 | D21: =COUNTIF(P4_Perf!$E$6:$E$600,"Done") -> 0 | E21: =COUNTIF(P4_Perf!$E$6:$E$600,"In progress") -> 0 | F21: =COUNTIF(P4_Perf!$E$6:$E$600,"Blocked") -> 0 | G21: =COUNTIF(P4_Perf!$E$6:$E$600,"Not started") -> 91 | H21: =COUNTIF(P4_Perf!$E$6:$E$600,"Skipped") -> 0 | I21: =IFERROR(D21/(C21-H21),0) -> 0 | J21: =IFERROR(INDEX(P4_Perf!$C$6:$C$600,MATCH("In progress",P4_Perf!$E$6:$E$600,0)),IFERROR(INDEX(P4_Perf!$C$6:$C$600,MATCH("Not started",P4_Perf!$E$6:$E$600,0)),"All items complete")) -> Define W1-W6: scan-heavy, shuffle-heavy, CPU-heavy (per-line score), memory-heavy (cache + wide aggregation), write-heavy (layout rewrite), mixed user-feature build.
A22: Project 5 | B22: Project 5: Streaming and CDC into Iceberg | C22: =SUM(D22:H22) -> 77 | D22: =COUNTIF(P5_Streaming!$E$6:$E$600,"Done") -> 0 | E22: =COUNTIF(P5_Streaming!$E$6:$E$600,"In progress") -> 0 | F22: =COUNTIF(P5_Streaming!$E$6:$E$600,"Blocked") -> 0 | G22: =COUNTIF(P5_Streaming!$E$6:$E$600,"Not started") -> 77 | H22: =COUNTIF(P5_Streaming!$E$6:$E$600,"Skipped") -> 0 | I22: =IFERROR(D22/(C22-H22),0) -> 0 | J22: =IFERROR(INDEX(P5_Streaming!$C$6:$C$600,MATCH("In progress",P5_Streaming!$E$6:$E$600,0)),IFERROR(INDEX(P5_Streaming!$C$6:$C$600,MATCH("Not started",P5_Streaming!$E$6:$E$600,0)),"All items complete")) -> Clickstream producer around real baskets, with duplicates/replays, malformed lines, schema drift, out-of-order events and ~2% very late events.
A24: SUPPORTING TRACKERS
A25: Tracker | B25: Measure | C25: Count
A26: Experiments | B26: Logged | C26: =COUNTA(Experiments!$A$7:$A$106) -> 0
A27: Experiments | B27: Prediction correct (Yes) | C27: =COUNTIF(Experiments!$M$7:$M$106,"Yes") -> 0
A28: Experiments | B28: Prediction accuracy (Yes / answered) | C28: =IFERROR(COUNTIF(Experiments!$M$7:$M$106,"Yes")/(COUNTIF(Experiments!$M$7:$M$106,"Yes")+COUNTIF(Experiments!$M$7:$M$106,"No")+COUNTIF(Experiments!$M$7:$M$106,"Partly")),0) -> 0
A29: Defects | B29: On the register | C29: =COUNTA(Defects!$A$7:$A$60) -> 11
A30: Defects | B30: Handled | C30: =COUNTIF(Defects!$M$7:$M$60,"Handled") -> 0
A31: Defects | B31: Still to verify | C31: =COUNTIF(Defects!$M$7:$M$60,"To verify") -> 11
A32: Decisions | B32: Decided | C32: =COUNTIF(Decisions!$H$7:$H$40,"Decided") -> 0
A33: Decisions | B33: Still open | C33: =COUNTIF(Decisions!$H$7:$H$40,"Open") -> 14
A34: Config cards | B34: Learned | C34: =COUNTIF(Config_Cards!$I$6:$I$38,"Learned") -> 0
A35: Config cards | B35: Total | C35: =COUNTA(Config_Cards!$B$6:$B$38) -> 33
A37: BY MILESTONE
A38: Area | B38: Milestone | C38: Total | D38: Done | E38: In progress | F38: Blocked | G38: Not started | H38: Skipped | I38: % complete
A39: SU | B39: S0 Gates and decisions | C39: =SUM(D39:H39) -> 5 | D39: =COUNTIFS(Setup!$B$6:$B$600,$B39,Setup!$E$6:$E$600,"Done") -> 0 | E39: =COUNTIFS(Setup!$B$6:$B$600,$B39,Setup!$E$6:$E$600,"In progress") -> 0 | F39: =COUNTIFS(Setup!$B$6:$B$600,$B39,Setup!$E$6:$E$600,"Blocked") -> 0 | G39: =COUNTIFS(Setup!$B$6:$B$600,$B39,Setup!$E$6:$E$600,"Not started") -> 5 | H39: =COUNTIFS(Setup!$B$6:$B$600,$B39,Setup!$E$6:$E$600,"Skipped") -> 0 | I39: =IFERROR(D39/(C39-H39),0) -> 0
A40: SU | B40: S1 Platform bring-up | C40: =SUM(D40:H40) -> 10 | D40: =COUNTIFS(Setup!$B$6:$B$600,$B40,Setup!$E$6:$E$600,"Done") -> 0 | E40: =COUNTIFS(Setup!$B$6:$B$600,$B40,Setup!$E$6:$E$600,"In progress") -> 0 | F40: =COUNTIFS(Setup!$B$6:$B$600,$B40,Setup!$E$6:$E$600,"Blocked") -> 0 | G40: =COUNTIFS(Setup!$B$6:$B$600,$B40,Setup!$E$6:$E$600,"Not started") -> 10 | H40: =COUNTIFS(Setup!$B$6:$B$600,$B40,Setup!$E$6:$E$600,"Skipped") -> 0 | I40: =IFERROR(D40/(C40-H40),0) -> 0
A41: SU | B41: S2 RustFS smoke tests | C41: =SUM(D41:H41) -> 8 | D41: =COUNTIFS(Setup!$B$6:$B$600,$B41,Setup!$E$6:$E$600,"Done") -> 0 | E41: =COUNTIFS(Setup!$B$6:$B$600,$B41,Setup!$E$6:$E$600,"In progress") -> 0 | F41: =COUNTIFS(Setup!$B$6:$B$600,$B41,Setup!$E$6:$E$600,"Blocked") -> 0 | G41: =COUNTIFS(Setup!$B$6:$B$600,$B41,Setup!$E$6:$E$600,"Not started") -> 8 | H41: =COUNTIFS(Setup!$B$6:$B$600,$B41,Setup!$E$6:$E$600,"Skipped") -> 0 | I41: =IFERROR(D41/(C41-H41),0) -> 0
A42: SU | B42: S3 Dataset acquisition | C42: =SUM(D42:H42) -> 6 | D42: =COUNTIFS(Setup!$B$6:$B$600,$B42,Setup!$E$6:$E$600,"Done") -> 0 | E42: =COUNTIFS(Setup!$B$6:$B$600,$B42,Setup!$E$6:$E$600,"In progress") -> 0 | F42: =COUNTIFS(Setup!$B$6:$B$600,$B42,Setup!$E$6:$E$600,"Blocked") -> 0 | G42: =COUNTIFS(Setup!$B$6:$B$600,$B42,Setup!$E$6:$E$600,"Not started") -> 6 | H42: =COUNTIFS(Setup!$B$6:$B$600,$B42,Setup!$E$6:$E$600,"Skipped") -> 0 | I42: =IFERROR(D42/(C42-H42),0) -> 0
A43: SU | B43: S4 Helpers | C43: =SUM(D43:H43) -> 12 | D43: =COUNTIFS(Setup!$B$6:$B$600,$B43,Setup!$E$6:$E$600,"Done") -> 0 | E43: =COUNTIFS(Setup!$B$6:$B$600,$B43,Setup!$E$6:$E$600,"In progress") -> 0 | F43: =COUNTIFS(Setup!$B$6:$B$600,$B43,Setup!$E$6:$E$600,"Blocked") -> 0 | G43: =COUNTIFS(Setup!$B$6:$B$600,$B43,Setup!$E$6:$E$600,"Not started") -> 12 | H43: =COUNTIFS(Setup!$B$6:$B$600,$B43,Setup!$E$6:$E$600,"Skipped") -> 0 | I43: =IFERROR(D43/(C43-H43),0) -> 0
A44: SU | B44: S5 Conventions | C44: =SUM(D44:H44) -> 6 | D44: =COUNTIFS(Setup!$B$6:$B$600,$B44,Setup!$E$6:$E$600,"Done") -> 0 | E44: =COUNTIFS(Setup!$B$6:$B$600,$B44,Setup!$E$6:$E$600,"In progress") -> 0 | F44: =COUNTIFS(Setup!$B$6:$B$600,$B44,Setup!$E$6:$E$600,"Blocked") -> 0 | G44: =COUNTIFS(Setup!$B$6:$B$600,$B44,Setup!$E$6:$E$600,"Not started") -> 6 | H44: =COUNTIFS(Setup!$B$6:$B$600,$B44,Setup!$E$6:$E$600,"Skipped") -> 0 | I44: =IFERROR(D44/(C44-H44),0) -> 0
A45: P1 | B45: M0 Load, profile, enrich | C45: =SUM(D45:H45) -> 19 | D45: =COUNTIFS(P1_ETL!$B$6:$B$600,$B45,P1_ETL!$E$6:$E$600,"Done") -> 0 | E45: =COUNTIFS(P1_ETL!$B$6:$B$600,$B45,P1_ETL!$E$6:$E$600,"In progress") -> 0 | F45: =COUNTIFS(P1_ETL!$B$6:$B$600,$B45,P1_ETL!$E$6:$E$600,"Blocked") -> 0 | G45: =COUNTIFS(P1_ETL!$B$6:$B$600,$B45,P1_ETL!$E$6:$E$600,"Not started") -> 19 | H45: =COUNTIFS(P1_ETL!$B$6:$B$600,$B45,P1_ETL!$E$6:$E$600,"Skipped") -> 0 | I45: =IFERROR(D45/(C45-H45),0) -> 0
A46: P1 | B46: M1 Full extraction | C46: =SUM(D46:H46) -> 13 | D46: =COUNTIFS(P1_ETL!$B$6:$B$600,$B46,P1_ETL!$E$6:$E$600,"Done") -> 0 | E46: =COUNTIFS(P1_ETL!$B$6:$B$600,$B46,P1_ETL!$E$6:$E$600,"In progress") -> 0 | F46: =COUNTIFS(P1_ETL!$B$6:$B$600,$B46,P1_ETL!$E$6:$E$600,"Blocked") -> 0 | G46: =COUNTIFS(P1_ETL!$B$6:$B$600,$B46,P1_ETL!$E$6:$E$600,"Not started") -> 13 | H46: =COUNTIFS(P1_ETL!$B$6:$B$600,$B46,P1_ETL!$E$6:$E$600,"Skipped") -> 0 | I46: =IFERROR(D46/(C46-H46),0) -> 0
A47: P1 | B47: M2 Incremental extraction | C47: =SUM(D47:H47) -> 11 | D47: =COUNTIFS(P1_ETL!$B$6:$B$600,$B47,P1_ETL!$E$6:$E$600,"Done") -> 0 | E47: =COUNTIFS(P1_ETL!$B$6:$B$600,$B47,P1_ETL!$E$6:$E$600,"In progress") -> 0 | F47: =COUNTIFS(P1_ETL!$B$6:$B$600,$B47,P1_ETL!$E$6:$E$600,"Blocked") -> 0 | G47: =COUNTIFS(P1_ETL!$B$6:$B$600,$B47,P1_ETL!$E$6:$E$600,"Not started") -> 11 | H47: =COUNTIFS(P1_ETL!$B$6:$B$600,$B47,P1_ETL!$E$6:$E$600,"Skipped") -> 0 | I47: =IFERROR(D47/(C47-H47),0) -> 0
A48: P1 | B48: M3 Bronze | C48: =SUM(D48:H48) -> 12 | D48: =COUNTIFS(P1_ETL!$B$6:$B$600,$B48,P1_ETL!$E$6:$E$600,"Done") -> 0 | E48: =COUNTIFS(P1_ETL!$B$6:$B$600,$B48,P1_ETL!$E$6:$E$600,"In progress") -> 0 | F48: =COUNTIFS(P1_ETL!$B$6:$B$600,$B48,P1_ETL!$E$6:$E$600,"Blocked") -> 0 | G48: =COUNTIFS(P1_ETL!$B$6:$B$600,$B48,P1_ETL!$E$6:$E$600,"Not started") -> 12 | H48: =COUNTIFS(P1_ETL!$B$6:$B$600,$B48,P1_ETL!$E$6:$E$600,"Skipped") -> 0 | I48: =IFERROR(D48/(C48-H48),0) -> 0
A49: P1 | B49: M4 Silver | C49: =SUM(D49:H49) -> 18 | D49: =COUNTIFS(P1_ETL!$B$6:$B$600,$B49,P1_ETL!$E$6:$E$600,"Done") -> 0 | E49: =COUNTIFS(P1_ETL!$B$6:$B$600,$B49,P1_ETL!$E$6:$E$600,"In progress") -> 0 | F49: =COUNTIFS(P1_ETL!$B$6:$B$600,$B49,P1_ETL!$E$6:$E$600,"Blocked") -> 0 | G49: =COUNTIFS(P1_ETL!$B$6:$B$600,$B49,P1_ETL!$E$6:$E$600,"Not started") -> 18 | H49: =COUNTIFS(P1_ETL!$B$6:$B$600,$B49,P1_ETL!$E$6:$E$600,"Skipped") -> 0 | I49: =IFERROR(D49/(C49-H49),0) -> 0
A50: P1 | B50: M5 Gold | C50: =SUM(D50:H50) -> 13 | D50: =COUNTIFS(P1_ETL!$B$6:$B$600,$B50,P1_ETL!$E$6:$E$600,"Done") -> 0 | E50: =COUNTIFS(P1_ETL!$B$6:$B$600,$B50,P1_ETL!$E$6:$E$600,"In progress") -> 0 | F50: =COUNTIFS(P1_ETL!$B$6:$B$600,$B50,P1_ETL!$E$6:$E$600,"Blocked") -> 0 | G50: =COUNTIFS(P1_ETL!$B$6:$B$600,$B50,P1_ETL!$E$6:$E$600,"Not started") -> 13 | H50: =COUNTIFS(P1_ETL!$B$6:$B$600,$B50,P1_ETL!$E$6:$E$600,"Skipped") -> 0 | I50: =IFERROR(D50/(C50-H50),0) -> 0
A51: P1 | B51: M6 Evolution and WAP | C51: =SUM(D51:H51) -> 7 | D51: =COUNTIFS(P1_ETL!$B$6:$B$600,$B51,P1_ETL!$E$6:$E$600,"Done") -> 0 | E51: =COUNTIFS(P1_ETL!$B$6:$B$600,$B51,P1_ETL!$E$6:$E$600,"In progress") -> 0 | F51: =COUNTIFS(P1_ETL!$B$6:$B$600,$B51,P1_ETL!$E$6:$E$600,"Blocked") -> 0 | G51: =COUNTIFS(P1_ETL!$B$6:$B$600,$B51,P1_ETL!$E$6:$E$600,"Not started") -> 7 | H51: =COUNTIFS(P1_ETL!$B$6:$B$600,$B51,P1_ETL!$E$6:$E$600,"Skipped") -> 0 | I51: =IFERROR(D51/(C51-H51),0) -> 0
A52: P1 | B52: M7 Maintenance | C52: =SUM(D52:H52) -> 10 | D52: =COUNTIFS(P1_ETL!$B$6:$B$600,$B52,P1_ETL!$E$6:$E$600,"Done") -> 0 | E52: =COUNTIFS(P1_ETL!$B$6:$B$600,$B52,P1_ETL!$E$6:$E$600,"In progress") -> 0 | F52: =COUNTIFS(P1_ETL!$B$6:$B$600,$B52,P1_ETL!$E$6:$E$600,"Blocked") -> 0 | G52: =COUNTIFS(P1_ETL!$B$6:$B$600,$B52,P1_ETL!$E$6:$E$600,"Not started") -> 10 | H52: =COUNTIFS(P1_ETL!$B$6:$B$600,$B52,P1_ETL!$E$6:$E$600,"Skipped") -> 0 | I52: =IFERROR(D52/(C52-H52),0) -> 0
A53: P1 | B53: M8 Orchestration and reconciliation | C53: =SUM(D53:H53) -> 10 | D53: =COUNTIFS(P1_ETL!$B$6:$B$600,$B53,P1_ETL!$E$6:$E$600,"Done") -> 0 | E53: =COUNTIFS(P1_ETL!$B$6:$B$600,$B53,P1_ETL!$E$6:$E$600,"In progress") -> 0 | F53: =COUNTIFS(P1_ETL!$B$6:$B$600,$B53,P1_ETL!$E$6:$E$600,"Blocked") -> 0 | G53: =COUNTIFS(P1_ETL!$B$6:$B$600,$B53,P1_ETL!$E$6:$E$600,"Not started") -> 10 | H53: =COUNTIFS(P1_ETL!$B$6:$B$600,$B53,P1_ETL!$E$6:$E$600,"Skipped") -> 0 | I53: =IFERROR(D53/(C53-H53),0) -> 0
A54: P2 | B54: M0 Test bed and baselines | C54: =SUM(D54:H54) -> 6 | D54: =COUNTIFS(P2_Joins!$B$6:$B$600,$B54,P2_Joins!$E$6:$E$600,"Done") -> 0 | E54: =COUNTIFS(P2_Joins!$B$6:$B$600,$B54,P2_Joins!$E$6:$E$600,"In progress") -> 0 | F54: =COUNTIFS(P2_Joins!$B$6:$B$600,$B54,P2_Joins!$E$6:$E$600,"Blocked") -> 0 | G54: =COUNTIFS(P2_Joins!$B$6:$B$600,$B54,P2_Joins!$E$6:$E$600,"Not started") -> 6 | H54: =COUNTIFS(P2_Joins!$B$6:$B$600,$B54,P2_Joins!$E$6:$E$600,"Skipped") -> 0 | I54: =IFERROR(D54/(C54-H54),0) -> 0
A55: P2 | B55: M1 Reading baseline plans | C55: =SUM(D55:H55) -> 6 | D55: =COUNTIFS(P2_Joins!$B$6:$B$600,$B55,P2_Joins!$E$6:$E$600,"Done") -> 0 | E55: =COUNTIFS(P2_Joins!$B$6:$B$600,$B55,P2_Joins!$E$6:$E$600,"In progress") -> 0 | F55: =COUNTIFS(P2_Joins!$B$6:$B$600,$B55,P2_Joins!$E$6:$E$600,"Blocked") -> 0 | G55: =COUNTIFS(P2_Joins!$B$6:$B$600,$B55,P2_Joins!$E$6:$E$600,"Not started") -> 6 | H55: =COUNTIFS(P2_Joins!$B$6:$B$600,$B55,P2_Joins!$E$6:$E$600,"Skipped") -> 0 | I55: =IFERROR(D55/(C55-H55),0) -> 0
A56: P2 | B56: M2 Join strategies by hint | C56: =SUM(D56:H56) -> 8 | D56: =COUNTIFS(P2_Joins!$B$6:$B$600,$B56,P2_Joins!$E$6:$E$600,"Done") -> 0 | E56: =COUNTIFS(P2_Joins!$B$6:$B$600,$B56,P2_Joins!$E$6:$E$600,"In progress") -> 0 | F56: =COUNTIFS(P2_Joins!$B$6:$B$600,$B56,P2_Joins!$E$6:$E$600,"Blocked") -> 0 | G56: =COUNTIFS(P2_Joins!$B$6:$B$600,$B56,P2_Joins!$E$6:$E$600,"Not started") -> 8 | H56: =COUNTIFS(P2_Joins!$B$6:$B$600,$B56,P2_Joins!$E$6:$E$600,"Skipped") -> 0 | I56: =IFERROR(D56/(C56-H56),0) -> 0
A57: P2 | B57: M3 Federated joins | C57: =SUM(D57:H57) -> 8 | D57: =COUNTIFS(P2_Joins!$B$6:$B$600,$B57,P2_Joins!$E$6:$E$600,"Done") -> 0 | E57: =COUNTIFS(P2_Joins!$B$6:$B$600,$B57,P2_Joins!$E$6:$E$600,"In progress") -> 0 | F57: =COUNTIFS(P2_Joins!$B$6:$B$600,$B57,P2_Joins!$E$6:$E$600,"Blocked") -> 0 | G57: =COUNTIFS(P2_Joins!$B$6:$B$600,$B57,P2_Joins!$E$6:$E$600,"Not started") -> 8 | H57: =COUNTIFS(P2_Joins!$B$6:$B$600,$B57,P2_Joins!$E$6:$E$600,"Skipped") -> 0 | I57: =IFERROR(D57/(C57-H57),0) -> 0
A58: P2 | B58: M4 Diagnosing skew | C58: =SUM(D58:H58) -> 5 | D58: =COUNTIFS(P2_Joins!$B$6:$B$600,$B58,P2_Joins!$E$6:$E$600,"Done") -> 0 | E58: =COUNTIFS(P2_Joins!$B$6:$B$600,$B58,P2_Joins!$E$6:$E$600,"In progress") -> 0 | F58: =COUNTIFS(P2_Joins!$B$6:$B$600,$B58,P2_Joins!$E$6:$E$600,"Blocked") -> 0 | G58: =COUNTIFS(P2_Joins!$B$6:$B$600,$B58,P2_Joins!$E$6:$E$600,"Not started") -> 5 | H58: =COUNTIFS(P2_Joins!$B$6:$B$600,$B58,P2_Joins!$E$6:$E$600,"Skipped") -> 0 | I58: =IFERROR(D58/(C58-H58),0) -> 0
A59: P2 | B59: M5 Skew-fix ladder | C59: =SUM(D59:H59) -> 8 | D59: =COUNTIFS(P2_Joins!$B$6:$B$600,$B59,P2_Joins!$E$6:$E$600,"Done") -> 0 | E59: =COUNTIFS(P2_Joins!$B$6:$B$600,$B59,P2_Joins!$E$6:$E$600,"In progress") -> 0 | F59: =COUNTIFS(P2_Joins!$B$6:$B$600,$B59,P2_Joins!$E$6:$E$600,"Blocked") -> 0 | G59: =COUNTIFS(P2_Joins!$B$6:$B$600,$B59,P2_Joins!$E$6:$E$600,"Not started") -> 8 | H59: =COUNTIFS(P2_Joins!$B$6:$B$600,$B59,P2_Joins!$E$6:$E$600,"Skipped") -> 0 | I59: =IFERROR(D59/(C59-H59),0) -> 0
A60: P2 | B60: M6 Pair explosion | C60: =SUM(D60:H60) -> 10 | D60: =COUNTIFS(P2_Joins!$B$6:$B$600,$B60,P2_Joins!$E$6:$E$600,"Done") -> 0 | E60: =COUNTIFS(P2_Joins!$B$6:$B$600,$B60,P2_Joins!$E$6:$E$600,"In progress") -> 0 | F60: =COUNTIFS(P2_Joins!$B$6:$B$600,$B60,P2_Joins!$E$6:$E$600,"Blocked") -> 0 | G60: =COUNTIFS(P2_Joins!$B$6:$B$600,$B60,P2_Joins!$E$6:$E$600,"Not started") -> 10 | H60: =COUNTIFS(P2_Joins!$B$6:$B$600,$B60,P2_Joins!$E$6:$E$600,"Skipped") -> 0 | I60: =IFERROR(D60/(C60-H60),0) -> 0
A61: P2 | B61: M7 Range joins | C61: =SUM(D61:H61) -> 8 | D61: =COUNTIFS(P2_Joins!$B$6:$B$600,$B61,P2_Joins!$E$6:$E$600,"Done") -> 0 | E61: =COUNTIFS(P2_Joins!$B$6:$B$600,$B61,P2_Joins!$E$6:$E$600,"In progress") -> 0 | F61: =COUNTIFS(P2_Joins!$B$6:$B$600,$B61,P2_Joins!$E$6:$E$600,"Blocked") -> 0 | G61: =COUNTIFS(P2_Joins!$B$6:$B$600,$B61,P2_Joins!$E$6:$E$600,"Not started") -> 8 | H61: =COUNTIFS(P2_Joins!$B$6:$B$600,$B61,P2_Joins!$E$6:$E$600,"Skipped") -> 0 | I61: =IFERROR(D61/(C61-H61),0) -> 0
A62: P2 | B62: M8 Partition sizing and writes | C62: =SUM(D62:H62) -> 5 | D62: =COUNTIFS(P2_Joins!$B$6:$B$600,$B62,P2_Joins!$E$6:$E$600,"Done") -> 0 | E62: =COUNTIFS(P2_Joins!$B$6:$B$600,$B62,P2_Joins!$E$6:$E$600,"In progress") -> 0 | F62: =COUNTIFS(P2_Joins!$B$6:$B$600,$B62,P2_Joins!$E$6:$E$600,"Blocked") -> 0 | G62: =COUNTIFS(P2_Joins!$B$6:$B$600,$B62,P2_Joins!$E$6:$E$600,"Not started") -> 5 | H62: =COUNTIFS(P2_Joins!$B$6:$B$600,$B62,P2_Joins!$E$6:$E$600,"Skipped") -> 0 | I62: =IFERROR(D62/(C62-H62),0) -> 0
A63: P2 | B63: M9 Storage-partitioned joins | C63: =SUM(D63:H63) -> 10 | D63: =COUNTIFS(P2_Joins!$B$6:$B$600,$B63,P2_Joins!$E$6:$E$600,"Done") -> 0 | E63: =COUNTIFS(P2_Joins!$B$6:$B$600,$B63,P2_Joins!$E$6:$E$600,"In progress") -> 0 | F63: =COUNTIFS(P2_Joins!$B$6:$B$600,$B63,P2_Joins!$E$6:$E$600,"Blocked") -> 0 | G63: =COUNTIFS(P2_Joins!$B$6:$B$600,$B63,P2_Joins!$E$6:$E$600,"Not started") -> 10 | H63: =COUNTIFS(P2_Joins!$B$6:$B$600,$B63,P2_Joins!$E$6:$E$600,"Skipped") -> 0 | I63: =IFERROR(D63/(C63-H63),0) -> 0
A64: P2 | B64: M10 Memory pressure and spill | C64: =SUM(D64:H64) -> 8 | D64: =COUNTIFS(P2_Joins!$B$6:$B$600,$B64,P2_Joins!$E$6:$E$600,"Done") -> 0 | E64: =COUNTIFS(P2_Joins!$B$6:$B$600,$B64,P2_Joins!$E$6:$E$600,"In progress") -> 0 | F64: =COUNTIFS(P2_Joins!$B$6:$B$600,$B64,P2_Joins!$E$6:$E$600,"Blocked") -> 0 | G64: =COUNTIFS(P2_Joins!$B$6:$B$600,$B64,P2_Joins!$E$6:$E$600,"Not started") -> 8 | H64: =COUNTIFS(P2_Joins!$B$6:$B$600,$B64,P2_Joins!$E$6:$E$600,"Skipped") -> 0 | I64: =IFERROR(D64/(C64-H64),0) -> 0
A65: P2 | B65: M11 Anti-pattern gallery | C65: =SUM(D65:H65) -> 7 | D65: =COUNTIFS(P2_Joins!$B$6:$B$600,$B65,P2_Joins!$E$6:$E$600,"Done") -> 0 | E65: =COUNTIFS(P2_Joins!$B$6:$B$600,$B65,P2_Joins!$E$6:$E$600,"In progress") -> 0 | F65: =COUNTIFS(P2_Joins!$B$6:$B$600,$B65,P2_Joins!$E$6:$E$600,"Blocked") -> 0 | G65: =COUNTIFS(P2_Joins!$B$6:$B$600,$B65,P2_Joins!$E$6:$E$600,"Not started") -> 7 | H65: =COUNTIFS(P2_Joins!$B$6:$B$600,$B65,P2_Joins!$E$6:$E$600,"Skipped") -> 0 | I65: =IFERROR(D65/(C65-H65),0) -> 0
A66: P2 | B66: M12 Synthesis | C66: =SUM(D66:H66) -> 2 | D66: =COUNTIFS(P2_Joins!$B$6:$B$600,$B66,P2_Joins!$E$6:$E$600,"Done") -> 0 | E66: =COUNTIFS(P2_Joins!$B$6:$B$600,$B66,P2_Joins!$E$6:$E$600,"In progress") -> 0 | F66: =COUNTIFS(P2_Joins!$B$6:$B$600,$B66,P2_Joins!$E$6:$E$600,"Blocked") -> 0 | G66: =COUNTIFS(P2_Joins!$B$6:$B$600,$B66,P2_Joins!$E$6:$E$600,"Not started") -> 2 | H66: =COUNTIFS(P2_Joins!$B$6:$B$600,$B66,P2_Joins!$E$6:$E$600,"Skipped") -> 0 | I66: =IFERROR(D66/(C66-H66),0) -> 0
A67: P3 | B67: M0 Variants and query suite | C67: =SUM(D67:H67) -> 5 | D67: =COUNTIFS(P3_Planner!$B$6:$B$600,$B67,P3_Planner!$E$6:$E$600,"Done") -> 0 | E67: =COUNTIFS(P3_Planner!$B$6:$B$600,$B67,P3_Planner!$E$6:$E$600,"In progress") -> 0 | F67: =COUNTIFS(P3_Planner!$B$6:$B$600,$B67,P3_Planner!$E$6:$E$600,"Blocked") -> 0 | G67: =COUNTIFS(P3_Planner!$B$6:$B$600,$B67,P3_Planner!$E$6:$E$600,"Not started") -> 5 | H67: =COUNTIFS(P3_Planner!$B$6:$B$600,$B67,P3_Planner!$E$6:$E$600,"Skipped") -> 0 | I67: =IFERROR(D67/(C67-H67),0) -> 0
A68: P3 | B68: M1 Plan literacy | C68: =SUM(D68:H68) -> 8 | D68: =COUNTIFS(P3_Planner!$B$6:$B$600,$B68,P3_Planner!$E$6:$E$600,"Done") -> 0 | E68: =COUNTIFS(P3_Planner!$B$6:$B$600,$B68,P3_Planner!$E$6:$E$600,"In progress") -> 0 | F68: =COUNTIFS(P3_Planner!$B$6:$B$600,$B68,P3_Planner!$E$6:$E$600,"Blocked") -> 0 | G68: =COUNTIFS(P3_Planner!$B$6:$B$600,$B68,P3_Planner!$E$6:$E$600,"Not started") -> 8 | H68: =COUNTIFS(P3_Planner!$B$6:$B$600,$B68,P3_Planner!$E$6:$E$600,"Skipped") -> 0 | I68: =IFERROR(D68/(C68-H68),0) -> 0
A69: P3 | B69: M2 Iceberg pruning | C69: =SUM(D69:H69) -> 10 | D69: =COUNTIFS(P3_Planner!$B$6:$B$600,$B69,P3_Planner!$E$6:$E$600,"Done") -> 0 | E69: =COUNTIFS(P3_Planner!$B$6:$B$600,$B69,P3_Planner!$E$6:$E$600,"In progress") -> 0 | F69: =COUNTIFS(P3_Planner!$B$6:$B$600,$B69,P3_Planner!$E$6:$E$600,"Blocked") -> 0 | G69: =COUNTIFS(P3_Planner!$B$6:$B$600,$B69,P3_Planner!$E$6:$E$600,"Not started") -> 10 | H69: =COUNTIFS(P3_Planner!$B$6:$B$600,$B69,P3_Planner!$E$6:$E$600,"Skipped") -> 0 | I69: =IFERROR(D69/(C69-H69),0) -> 0
A70: P3 | B70: M3 Runtime filtering | C70: =SUM(D70:H70) -> 5 | D70: =COUNTIFS(P3_Planner!$B$6:$B$600,$B70,P3_Planner!$E$6:$E$600,"Done") -> 0 | E70: =COUNTIFS(P3_Planner!$B$6:$B$600,$B70,P3_Planner!$E$6:$E$600,"In progress") -> 0 | F70: =COUNTIFS(P3_Planner!$B$6:$B$600,$B70,P3_Planner!$E$6:$E$600,"Blocked") -> 0 | G70: =COUNTIFS(P3_Planner!$B$6:$B$600,$B70,P3_Planner!$E$6:$E$600,"Not started") -> 5 | H70: =COUNTIFS(P3_Planner!$B$6:$B$600,$B70,P3_Planner!$E$6:$E$600,"Skipped") -> 0 | I70: =IFERROR(D70/(C70-H70),0) -> 0
A71: P3 | B71: M4 Statistics and cost-based planning | C71: =SUM(D71:H71) -> 7 | D71: =COUNTIFS(P3_Planner!$B$6:$B$600,$B71,P3_Planner!$E$6:$E$600,"Done") -> 0 | E71: =COUNTIFS(P3_Planner!$B$6:$B$600,$B71,P3_Planner!$E$6:$E$600,"In progress") -> 0 | F71: =COUNTIFS(P3_Planner!$B$6:$B$600,$B71,P3_Planner!$E$6:$E$600,"Blocked") -> 0 | G71: =COUNTIFS(P3_Planner!$B$6:$B$600,$B71,P3_Planner!$E$6:$E$600,"Not started") -> 7 | H71: =COUNTIFS(P3_Planner!$B$6:$B$600,$B71,P3_Planner!$E$6:$E$600,"Skipped") -> 0 | I71: =IFERROR(D71/(C71-H71),0) -> 0
A72: P3 | B72: M5 JDBC pushdown | C72: =SUM(D72:H72) -> 13 | D72: =COUNTIFS(P3_Planner!$B$6:$B$600,$B72,P3_Planner!$E$6:$E$600,"Done") -> 0 | E72: =COUNTIFS(P3_Planner!$B$6:$B$600,$B72,P3_Planner!$E$6:$E$600,"In progress") -> 0 | F72: =COUNTIFS(P3_Planner!$B$6:$B$600,$B72,P3_Planner!$E$6:$E$600,"Blocked") -> 0 | G72: =COUNTIFS(P3_Planner!$B$6:$B$600,$B72,P3_Planner!$E$6:$E$600,"Not started") -> 13 | H72: =COUNTIFS(P3_Planner!$B$6:$B$600,$B72,P3_Planner!$E$6:$E$600,"Skipped") -> 0 | I72: =IFERROR(D72/(C72-H72),0) -> 0
A73: P3 | B73: M6 AQE re-planning | C73: =SUM(D73:H73) -> 5 | D73: =COUNTIFS(P3_Planner!$B$6:$B$600,$B73,P3_Planner!$E$6:$E$600,"Done") -> 0 | E73: =COUNTIFS(P3_Planner!$B$6:$B$600,$B73,P3_Planner!$E$6:$E$600,"In progress") -> 0 | F73: =COUNTIFS(P3_Planner!$B$6:$B$600,$B73,P3_Planner!$E$6:$E$600,"Blocked") -> 0 | G73: =COUNTIFS(P3_Planner!$B$6:$B$600,$B73,P3_Planner!$E$6:$E$600,"Not started") -> 5 | H73: =COUNTIFS(P3_Planner!$B$6:$B$600,$B73,P3_Planner!$E$6:$E$600,"Skipped") -> 0 | I73: =IFERROR(D73/(C73-H73),0) -> 0
A74: P3 | B74: M7 Whole-stage codegen | C74: =SUM(D74:H74) -> 5 | D74: =COUNTIFS(P3_Planner!$B$6:$B$600,$B74,P3_Planner!$E$6:$E$600,"Done") -> 0 | E74: =COUNTIFS(P3_Planner!$B$6:$B$600,$B74,P3_Planner!$E$6:$E$600,"In progress") -> 0 | F74: =COUNTIFS(P3_Planner!$B$6:$B$600,$B74,P3_Planner!$E$6:$E$600,"Blocked") -> 0 | G74: =COUNTIFS(P3_Planner!$B$6:$B$600,$B74,P3_Planner!$E$6:$E$600,"Not started") -> 5 | H74: =COUNTIFS(P3_Planner!$B$6:$B$600,$B74,P3_Planner!$E$6:$E$600,"Skipped") -> 0 | I74: =IFERROR(D74/(C74-H74),0) -> 0
A75: P3 | B75: M8 Optimizer blockers | C75: =SUM(D75:H75) -> 12 | D75: =COUNTIFS(P3_Planner!$B$6:$B$600,$B75,P3_Planner!$E$6:$E$600,"Done") -> 0 | E75: =COUNTIFS(P3_Planner!$B$6:$B$600,$B75,P3_Planner!$E$6:$E$600,"In progress") -> 0 | F75: =COUNTIFS(P3_Planner!$B$6:$B$600,$B75,P3_Planner!$E$6:$E$600,"Blocked") -> 0 | G75: =COUNTIFS(P3_Planner!$B$6:$B$600,$B75,P3_Planner!$E$6:$E$600,"Not started") -> 12 | H75: =COUNTIFS(P3_Planner!$B$6:$B$600,$B75,P3_Planner!$E$6:$E$600,"Skipped") -> 0 | I75: =IFERROR(D75/(C75-H75),0) -> 0
A76: P3 | B76: M9 Layout optimization | C76: =SUM(D76:H76) -> 7 | D76: =COUNTIFS(P3_Planner!$B$6:$B$600,$B76,P3_Planner!$E$6:$E$600,"Done") -> 0 | E76: =COUNTIFS(P3_Planner!$B$6:$B$600,$B76,P3_Planner!$E$6:$E$600,"In progress") -> 0 | F76: =COUNTIFS(P3_Planner!$B$6:$B$600,$B76,P3_Planner!$E$6:$E$600,"Blocked") -> 0 | G76: =COUNTIFS(P3_Planner!$B$6:$B$600,$B76,P3_Planner!$E$6:$E$600,"Not started") -> 7 | H76: =COUNTIFS(P3_Planner!$B$6:$B$600,$B76,P3_Planner!$E$6:$E$600,"Skipped") -> 0 | I76: =IFERROR(D76/(C76-H76),0) -> 0
A77: P3 | B77: M10 Synthesis | C77: =SUM(D77:H77) -> 2 | D77: =COUNTIFS(P3_Planner!$B$6:$B$600,$B77,P3_Planner!$E$6:$E$600,"Done") -> 0 | E77: =COUNTIFS(P3_Planner!$B$6:$B$600,$B77,P3_Planner!$E$6:$E$600,"In progress") -> 0 | F77: =COUNTIFS(P3_Planner!$B$6:$B$600,$B77,P3_Planner!$E$6:$E$600,"Blocked") -> 0 | G77: =COUNTIFS(P3_Planner!$B$6:$B$600,$B77,P3_Planner!$E$6:$E$600,"Not started") -> 2 | H77: =COUNTIFS(P3_Planner!$B$6:$B$600,$B77,P3_Planner!$E$6:$E$600,"Skipped") -> 0 | I77: =IFERROR(D77/(C77-H77),0) -> 0
A78: P4 | B78: M0 Workloads and baselines | C78: =SUM(D78:H78) -> 5 | D78: =COUNTIFS(P4_Perf!$B$6:$B$600,$B78,P4_Perf!$E$6:$E$600,"Done") -> 0 | E78: =COUNTIFS(P4_Perf!$B$6:$B$600,$B78,P4_Perf!$E$6:$E$600,"In progress") -> 0 | F78: =COUNTIFS(P4_Perf!$B$6:$B$600,$B78,P4_Perf!$E$6:$E$600,"Blocked") -> 0 | G78: =COUNTIFS(P4_Perf!$B$6:$B$600,$B78,P4_Perf!$E$6:$E$600,"Not started") -> 5 | H78: =COUNTIFS(P4_Perf!$B$6:$B$600,$B78,P4_Perf!$E$6:$E$600,"Skipped") -> 0 | I78: =IFERROR(D78/(C78-H78),0) -> 0
A79: P4 | B79: M1 Topology and strong scaling | C79: =SUM(D79:H79) -> 9 | D79: =COUNTIFS(P4_Perf!$B$6:$B$600,$B79,P4_Perf!$E$6:$E$600,"Done") -> 0 | E79: =COUNTIFS(P4_Perf!$B$6:$B$600,$B79,P4_Perf!$E$6:$E$600,"In progress") -> 0 | F79: =COUNTIFS(P4_Perf!$B$6:$B$600,$B79,P4_Perf!$E$6:$E$600,"Blocked") -> 0 | G79: =COUNTIFS(P4_Perf!$B$6:$B$600,$B79,P4_Perf!$E$6:$E$600,"Not started") -> 9 | H79: =COUNTIFS(P4_Perf!$B$6:$B$600,$B79,P4_Perf!$E$6:$E$600,"Skipped") -> 0 | I79: =IFERROR(D79/(C79-H79),0) -> 0
A80: P4 | B80: M2 Memory model | C80: =SUM(D80:H80) -> 10 | D80: =COUNTIFS(P4_Perf!$B$6:$B$600,$B80,P4_Perf!$E$6:$E$600,"Done") -> 0 | E80: =COUNTIFS(P4_Perf!$B$6:$B$600,$B80,P4_Perf!$E$6:$E$600,"In progress") -> 0 | F80: =COUNTIFS(P4_Perf!$B$6:$B$600,$B80,P4_Perf!$E$6:$E$600,"Blocked") -> 0 | G80: =COUNTIFS(P4_Perf!$B$6:$B$600,$B80,P4_Perf!$E$6:$E$600,"Not started") -> 10 | H80: =COUNTIFS(P4_Perf!$B$6:$B$600,$B80,P4_Perf!$E$6:$E$600,"Skipped") -> 0 | I80: =IFERROR(D80/(C80-H80),0) -> 0
A81: P4 | B81: M3 Serialization and RDD | C81: =SUM(D81:H81) -> 6 | D81: =COUNTIFS(P4_Perf!$B$6:$B$600,$B81,P4_Perf!$E$6:$E$600,"Done") -> 0 | E81: =COUNTIFS(P4_Perf!$B$6:$B$600,$B81,P4_Perf!$E$6:$E$600,"In progress") -> 0 | F81: =COUNTIFS(P4_Perf!$B$6:$B$600,$B81,P4_Perf!$E$6:$E$600,"Blocked") -> 0 | G81: =COUNTIFS(P4_Perf!$B$6:$B$600,$B81,P4_Perf!$E$6:$E$600,"Not started") -> 6 | H81: =COUNTIFS(P4_Perf!$B$6:$B$600,$B81,P4_Perf!$E$6:$E$600,"Skipped") -> 0 | I81: =IFERROR(D81/(C81-H81),0) -> 0
A82: P4 | B82: M4 Python UDF ladder | C82: =SUM(D82:H82) -> 13 | D82: =COUNTIFS(P4_Perf!$B$6:$B$600,$B82,P4_Perf!$E$6:$E$600,"Done") -> 0 | E82: =COUNTIFS(P4_Perf!$B$6:$B$600,$B82,P4_Perf!$E$6:$E$600,"In progress") -> 0 | F82: =COUNTIFS(P4_Perf!$B$6:$B$600,$B82,P4_Perf!$E$6:$E$600,"Blocked") -> 0 | G82: =COUNTIFS(P4_Perf!$B$6:$B$600,$B82,P4_Perf!$E$6:$E$600,"Not started") -> 13 | H82: =COUNTIFS(P4_Perf!$B$6:$B$600,$B82,P4_Perf!$E$6:$E$600,"Skipped") -> 0 | I82: =IFERROR(D82/(C82-H82),0) -> 0
A83: P4 | B83: M5 Object-store tuning | C83: =SUM(D83:H83) -> 12 | D83: =COUNTIFS(P4_Perf!$B$6:$B$600,$B83,P4_Perf!$E$6:$E$600,"Done") -> 0 | E83: =COUNTIFS(P4_Perf!$B$6:$B$600,$B83,P4_Perf!$E$6:$E$600,"In progress") -> 0 | F83: =COUNTIFS(P4_Perf!$B$6:$B$600,$B83,P4_Perf!$E$6:$E$600,"Blocked") -> 0 | G83: =COUNTIFS(P4_Perf!$B$6:$B$600,$B83,P4_Perf!$E$6:$E$600,"Not started") -> 12 | H83: =COUNTIFS(P4_Perf!$B$6:$B$600,$B83,P4_Perf!$E$6:$E$600,"Skipped") -> 0 | I83: =IFERROR(D83/(C83-H83),0) -> 0
A84: P4 | B84: M6 JDBC concurrency | C84: =SUM(D84:H84) -> 8 | D84: =COUNTIFS(P4_Perf!$B$6:$B$600,$B84,P4_Perf!$E$6:$E$600,"Done") -> 0 | E84: =COUNTIFS(P4_Perf!$B$6:$B$600,$B84,P4_Perf!$E$6:$E$600,"In progress") -> 0 | F84: =COUNTIFS(P4_Perf!$B$6:$B$600,$B84,P4_Perf!$E$6:$E$600,"Blocked") -> 0 | G84: =COUNTIFS(P4_Perf!$B$6:$B$600,$B84,P4_Perf!$E$6:$E$600,"Not started") -> 8 | H84: =COUNTIFS(P4_Perf!$B$6:$B$600,$B84,P4_Perf!$E$6:$E$600,"Skipped") -> 0 | I84: =IFERROR(D84/(C84-H84),0) -> 0
A85: P4 | B85: M7 Concurrent writers | C85: =SUM(D85:H85) -> 9 | D85: =COUNTIFS(P4_Perf!$B$6:$B$600,$B85,P4_Perf!$E$6:$E$600,"Done") -> 0 | E85: =COUNTIFS(P4_Perf!$B$6:$B$600,$B85,P4_Perf!$E$6:$E$600,"In progress") -> 0 | F85: =COUNTIFS(P4_Perf!$B$6:$B$600,$B85,P4_Perf!$E$6:$E$600,"Blocked") -> 0 | G85: =COUNTIFS(P4_Perf!$B$6:$B$600,$B85,P4_Perf!$E$6:$E$600,"Not started") -> 9 | H85: =COUNTIFS(P4_Perf!$B$6:$B$600,$B85,P4_Perf!$E$6:$E$600,"Skipped") -> 0 | I85: =IFERROR(D85/(C85-H85),0) -> 0
A86: P4 | B86: M8 Scheduling and allocation | C86: =SUM(D86:H86) -> 5 | D86: =COUNTIFS(P4_Perf!$B$6:$B$600,$B86,P4_Perf!$E$6:$E$600,"Done") -> 0 | E86: =COUNTIFS(P4_Perf!$B$6:$B$600,$B86,P4_Perf!$E$6:$E$600,"In progress") -> 0 | F86: =COUNTIFS(P4_Perf!$B$6:$B$600,$B86,P4_Perf!$E$6:$E$600,"Blocked") -> 0 | G86: =COUNTIFS(P4_Perf!$B$6:$B$600,$B86,P4_Perf!$E$6:$E$600,"Not started") -> 5 | H86: =COUNTIFS(P4_Perf!$B$6:$B$600,$B86,P4_Perf!$E$6:$E$600,"Skipped") -> 0 | I86: =IFERROR(D86/(C86-H86),0) -> 0
A87: P4 | B87: M9 Resilience | C87: =SUM(D87:H87) -> 7 | D87: =COUNTIFS(P4_Perf!$B$6:$B$600,$B87,P4_Perf!$E$6:$E$600,"Done") -> 0 | E87: =COUNTIFS(P4_Perf!$B$6:$B$600,$B87,P4_Perf!$E$6:$E$600,"In progress") -> 0 | F87: =COUNTIFS(P4_Perf!$B$6:$B$600,$B87,P4_Perf!$E$6:$E$600,"Blocked") -> 0 | G87: =COUNTIFS(P4_Perf!$B$6:$B$600,$B87,P4_Perf!$E$6:$E$600,"Not started") -> 7 | H87: =COUNTIFS(P4_Perf!$B$6:$B$600,$B87,P4_Perf!$E$6:$E$600,"Skipped") -> 0 | I87: =IFERROR(D87/(C87-H87),0) -> 0
A88: P4 | B88: M10 Shuffle internals | C88: =SUM(D88:H88) -> 5 | D88: =COUNTIFS(P4_Perf!$B$6:$B$600,$B88,P4_Perf!$E$6:$E$600,"Done") -> 0 | E88: =COUNTIFS(P4_Perf!$B$6:$B$600,$B88,P4_Perf!$E$6:$E$600,"In progress") -> 0 | F88: =COUNTIFS(P4_Perf!$B$6:$B$600,$B88,P4_Perf!$E$6:$E$600,"Blocked") -> 0 | G88: =COUNTIFS(P4_Perf!$B$6:$B$600,$B88,P4_Perf!$E$6:$E$600,"Not started") -> 5 | H88: =COUNTIFS(P4_Perf!$B$6:$B$600,$B88,P4_Perf!$E$6:$E$600,"Skipped") -> 0 | I88: =IFERROR(D88/(C88-H88),0) -> 0
A89: P4 | B89: M11 Capacity model | C89: =SUM(D89:H89) -> 2 | D89: =COUNTIFS(P4_Perf!$B$6:$B$600,$B89,P4_Perf!$E$6:$E$600,"Done") -> 0 | E89: =COUNTIFS(P4_Perf!$B$6:$B$600,$B89,P4_Perf!$E$6:$E$600,"In progress") -> 0 | F89: =COUNTIFS(P4_Perf!$B$6:$B$600,$B89,P4_Perf!$E$6:$E$600,"Blocked") -> 0 | G89: =COUNTIFS(P4_Perf!$B$6:$B$600,$B89,P4_Perf!$E$6:$E$600,"Not started") -> 2 | H89: =COUNTIFS(P4_Perf!$B$6:$B$600,$B89,P4_Perf!$E$6:$E$600,"Skipped") -> 0 | I89: =IFERROR(D89/(C89-H89),0) -> 0
A90: P5 | B90: M0 Sources, speeds, SLOs | C90: =SUM(D90:H90) -> 8 | D90: =COUNTIFS(P5_Streaming!$B$6:$B$600,$B90,P5_Streaming!$E$6:$E$600,"Done") -> 0 | E90: =COUNTIFS(P5_Streaming!$B$6:$B$600,$B90,P5_Streaming!$E$6:$E$600,"In progress") -> 0 | F90: =COUNTIFS(P5_Streaming!$B$6:$B$600,$B90,P5_Streaming!$E$6:$E$600,"Blocked") -> 0 | G90: =COUNTIFS(P5_Streaming!$B$6:$B$600,$B90,P5_Streaming!$E$6:$E$600,"Not started") -> 8 | H90: =COUNTIFS(P5_Streaming!$B$6:$B$600,$B90,P5_Streaming!$E$6:$E$600,"Skipped") -> 0 | I90: =IFERROR(D90/(C90-H90),0) -> 0
A91: P5 | B91: M1 Clickstream to bronze | C91: =SUM(D91:H91) -> 9 | D91: =COUNTIFS(P5_Streaming!$B$6:$B$600,$B91,P5_Streaming!$E$6:$E$600,"Done") -> 0 | E91: =COUNTIFS(P5_Streaming!$B$6:$B$600,$B91,P5_Streaming!$E$6:$E$600,"In progress") -> 0 | F91: =COUNTIFS(P5_Streaming!$B$6:$B$600,$B91,P5_Streaming!$E$6:$E$600,"Blocked") -> 0 | G91: =COUNTIFS(P5_Streaming!$B$6:$B$600,$B91,P5_Streaming!$E$6:$E$600,"Not started") -> 9 | H91: =COUNTIFS(P5_Streaming!$B$6:$B$600,$B91,P5_Streaming!$E$6:$E$600,"Skipped") -> 0 | I91: =IFERROR(D91/(C91-H91),0) -> 0
A92: P5 | B92: M2 Small files and maintenance | C92: =SUM(D92:H92) -> 6 | D92: =COUNTIFS(P5_Streaming!$B$6:$B$600,$B92,P5_Streaming!$E$6:$E$600,"Done") -> 0 | E92: =COUNTIFS(P5_Streaming!$B$6:$B$600,$B92,P5_Streaming!$E$6:$E$600,"In progress") -> 0 | F92: =COUNTIFS(P5_Streaming!$B$6:$B$600,$B92,P5_Streaming!$E$6:$E$600,"Blocked") -> 0 | G92: =COUNTIFS(P5_Streaming!$B$6:$B$600,$B92,P5_Streaming!$E$6:$E$600,"Not started") -> 6 | H92: =COUNTIFS(P5_Streaming!$B$6:$B$600,$B92,P5_Streaming!$E$6:$E$600,"Skipped") -> 0 | I92: =IFERROR(D92/(C92-H92),0) -> 0
A93: P5 | B93: M3 Windowed aggregates | C93: =SUM(D93:H93) -> 7 | D93: =COUNTIFS(P5_Streaming!$B$6:$B$600,$B93,P5_Streaming!$E$6:$E$600,"Done") -> 0 | E93: =COUNTIFS(P5_Streaming!$B$6:$B$600,$B93,P5_Streaming!$E$6:$E$600,"In progress") -> 0 | F93: =COUNTIFS(P5_Streaming!$B$6:$B$600,$B93,P5_Streaming!$E$6:$E$600,"Blocked") -> 0 | G93: =COUNTIFS(P5_Streaming!$B$6:$B$600,$B93,P5_Streaming!$E$6:$E$600,"Not started") -> 7 | H93: =COUNTIFS(P5_Streaming!$B$6:$B$600,$B93,P5_Streaming!$E$6:$E$600,"Skipped") -> 0 | I93: =IFERROR(D93/(C93-H93),0) -> 0
A94: P5 | B94: M4 Sessionization | C94: =SUM(D94:H94) -> 7 | D94: =COUNTIFS(P5_Streaming!$B$6:$B$600,$B94,P5_Streaming!$E$6:$E$600,"Done") -> 0 | E94: =COUNTIFS(P5_Streaming!$B$6:$B$600,$B94,P5_Streaming!$E$6:$E$600,"In progress") -> 0 | F94: =COUNTIFS(P5_Streaming!$B$6:$B$600,$B94,P5_Streaming!$E$6:$E$600,"Blocked") -> 0 | G94: =COUNTIFS(P5_Streaming!$B$6:$B$600,$B94,P5_Streaming!$E$6:$E$600,"Not started") -> 7 | H94: =COUNTIFS(P5_Streaming!$B$6:$B$600,$B94,P5_Streaming!$E$6:$E$600,"Skipped") -> 0 | I94: =IFERROR(D94/(C94-H94),0) -> 0
A95: P5 | B95: M5 CDC apply | C95: =SUM(D95:H95) -> 11 | D95: =COUNTIFS(P5_Streaming!$B$6:$B$600,$B95,P5_Streaming!$E$6:$E$600,"Done") -> 0 | E95: =COUNTIFS(P5_Streaming!$B$6:$B$600,$B95,P5_Streaming!$E$6:$E$600,"In progress") -> 0 | F95: =COUNTIFS(P5_Streaming!$B$6:$B$600,$B95,P5_Streaming!$E$6:$E$600,"Blocked") -> 0 | G95: =COUNTIFS(P5_Streaming!$B$6:$B$600,$B95,P5_Streaming!$E$6:$E$600,"Not started") -> 11 | H95: =COUNTIFS(P5_Streaming!$B$6:$B$600,$B95,P5_Streaming!$E$6:$E$600,"Skipped") -> 0 | I95: =IFERROR(D95/(C95-H95),0) -> 0
A96: P5 | B96: M6 Dedup and joins | C96: =SUM(D96:H96) -> 7 | D96: =COUNTIFS(P5_Streaming!$B$6:$B$600,$B96,P5_Streaming!$E$6:$E$600,"Done") -> 0 | E96: =COUNTIFS(P5_Streaming!$B$6:$B$600,$B96,P5_Streaming!$E$6:$E$600,"In progress") -> 0 | F96: =COUNTIFS(P5_Streaming!$B$6:$B$600,$B96,P5_Streaming!$E$6:$E$600,"Blocked") -> 0 | G96: =COUNTIFS(P5_Streaming!$B$6:$B$600,$B96,P5_Streaming!$E$6:$E$600,"Not started") -> 7 | H96: =COUNTIFS(P5_Streaming!$B$6:$B$600,$B96,P5_Streaming!$E$6:$E$600,"Skipped") -> 0 | I96: =IFERROR(D96/(C96-H96),0) -> 0
A97: P5 | B97: M7 State and throughput tuning | C97: =SUM(D97:H97) -> 6 | D97: =COUNTIFS(P5_Streaming!$B$6:$B$600,$B97,P5_Streaming!$E$6:$E$600,"Done") -> 0 | E97: =COUNTIFS(P5_Streaming!$B$6:$B$600,$B97,P5_Streaming!$E$6:$E$600,"In progress") -> 0 | F97: =COUNTIFS(P5_Streaming!$B$6:$B$600,$B97,P5_Streaming!$E$6:$E$600,"Blocked") -> 0 | G97: =COUNTIFS(P5_Streaming!$B$6:$B$600,$B97,P5_Streaming!$E$6:$E$600,"Not started") -> 6 | H97: =COUNTIFS(P5_Streaming!$B$6:$B$600,$B97,P5_Streaming!$E$6:$E$600,"Skipped") -> 0 | I97: =IFERROR(D97/(C97-H97),0) -> 0
A98: P5 | B98: M8 Failure drills | C98: =SUM(D98:H98) -> 8 | D98: =COUNTIFS(P5_Streaming!$B$6:$B$600,$B98,P5_Streaming!$E$6:$E$600,"Done") -> 0 | E98: =COUNTIFS(P5_Streaming!$B$6:$B$600,$B98,P5_Streaming!$E$6:$E$600,"In progress") -> 0 | F98: =COUNTIFS(P5_Streaming!$B$6:$B$600,$B98,P5_Streaming!$E$6:$E$600,"Blocked") -> 0 | G98: =COUNTIFS(P5_Streaming!$B$6:$B$600,$B98,P5_Streaming!$E$6:$E$600,"Not started") -> 8 | H98: =COUNTIFS(P5_Streaming!$B$6:$B$600,$B98,P5_Streaming!$E$6:$E$600,"Skipped") -> 0 | I98: =IFERROR(D98/(C98-H98),0) -> 0
A99: P5 | B99: M9 Latency and SLOs | C99: =SUM(D99:H99) -> 6 | D99: =COUNTIFS(P5_Streaming!$B$6:$B$600,$B99,P5_Streaming!$E$6:$E$600,"Done") -> 0 | E99: =COUNTIFS(P5_Streaming!$B$6:$B$600,$B99,P5_Streaming!$E$6:$E$600,"In progress") -> 0 | F99: =COUNTIFS(P5_Streaming!$B$6:$B$600,$B99,P5_Streaming!$E$6:$E$600,"Blocked") -> 0 | G99: =COUNTIFS(P5_Streaming!$B$6:$B$600,$B99,P5_Streaming!$E$6:$E$600,"Not started") -> 6 | H99: =COUNTIFS(P5_Streaming!$B$6:$B$600,$B99,P5_Streaming!$E$6:$E$600,"Skipped") -> 0 | I99: =IFERROR(D99/(C99-H99),0) -> 0
A100: P5 | B100: M10 Synthesis | C100: =SUM(D100:H100) -> 2 | D100: =COUNTIFS(P5_Streaming!$B$6:$B$600,$B100,P5_Streaming!$E$6:$E$600,"Done") -> 0 | E100: =COUNTIFS(P5_Streaming!$B$6:$B$600,$B100,P5_Streaming!$E$6:$E$600,"In progress") -> 0 | F100: =COUNTIFS(P5_Streaming!$B$6:$B$600,$B100,P5_Streaming!$E$6:$E$600,"Blocked") -> 0 | G100: =COUNTIFS(P5_Streaming!$B$6:$B$600,$B100,P5_Streaming!$E$6:$E$600,"Not started") -> 2 | H100: =COUNTIFS(P5_Streaming!$B$6:$B$600,$B100,P5_Streaming!$E$6:$E$600,"Skipped") -> 0 | I100: =IFERROR(D100/(C100-H100),0) -> 0

Sheet Setup
A1: Setup and gates
A2: Source: README sections 2-3 (bring-up and gates). Edit only the yellow cells: Status (dropdown), Started, Completed, Evidence / notes.
A3: Progress | B3: =IFERROR(COUNTIF($E$6:$E$600,"Done")/(COUNTA($E$6:$E$600)-COUNTIF($E$6:$E$600,"Skipped")),0) -> 0 | C3: =COUNTIF($E$6:$E$600,"Done")&" of "&(COUNTA($E$6:$E$600)-COUNTIF($E$6:$E$600,"Skipped"))&" items done | In progress: "&COUNTIF($E$6:$E$600,"In progress")&" | Blocked: "&COUNTIF($E$6:$E$600,"Blocked")&" | Skipped: "&COUNTIF($E$6:$E$600,"Skipped") -> 0 of 47 items done | In progress: 0 | Blocked: 0 | Skipped: 0
A5: ID | B5: Milestone | C5: Task | D5: Type | E5: Status | F5: Started | G5: Completed | H5: Evidence / notes
A6: S0 Gates and decisions
A7: SU-S0-01 | B7: S0 Gates and decisions | C7: Gate A: find the Iceberg Spark runtime artifact that matches your Spark minor version (Scala 2.13) on Maven Central. If the Spark 4.2 runtime is missing, pin Spark to the newest 4.x that has one. Record in Environment and Decisions. | D7: Task | E7: Not started
A8: SU-S0-02 | B8: S0 Gates and decisions | C8: Gate C: decide how the Iceberg runtime, the S3 access bundle (S3A + matching AWS SDK, or Iceberg AWS bundle) and the Postgres JDBC driver reach the driver and every executor (baked in vs resolved at runtime). | D8: Task | E8: Not started
A9: SU-S0-03 | B9: S0 Gates and decisions | C9: Gate D: choose the catalog (recommended: JDBC on Postgres, separate database). Record in Decisions. | D9: Task | E9: Not started
A10: SU-S0-04 | B10: S0 Gates and decisions | C10: Gate E: plan Postgres capacity for ~34M order lines (disk, memory, bulk load then index) and decide what stays in Postgres vs files only. | D10: Task | E10: Not started
A11: SU-S0-05 | B11: S0 Gates and decisions | C11: Set explicit CPU and memory limits on Postgres and RustFS (or record that you left them off on purpose). | D11: Task | E11: Not started
A12: S1 Platform bring-up
A13: SU-S1-01 | B13: S1 Platform bring-up | C13: 1. RustFS running (pinned release tag, changed credentials). Log in to the console, create buckets landing, warehouse, checkpoints, spark-events, archive; list them with an S3 client. | D13: Task | E13: Not started
A14: SU-S1-02 | B14: S1 Platform bring-up | C14: 2. PostgreSQL running with two databases (source, catalog). Connect from your laptop and from the Jupyter container. | D14: Task | E14: Not started
A15: SU-S1-03 | B15: S1 Platform bring-up | C15: 3. Spark cluster running. Master UI shows 4 workers, each with 2 cores and 2 GB. | D15: Task | E15: Not started
A16: SU-S1-04 | B16: S1 Platform bring-up | C16: 4. Jars resolved. A session starts with the Iceberg runtime, S3 access and the JDBC driver on the driver and on executors. | D16: Task | E16: Not started
A17: SU-S1-05 | B17: S1 Platform bring-up | C17: 5. Catalog configured. Create and drop a test namespace. | D17: Task | E17: Not started
A18: SU-S1-06 | B18: S1 Platform bring-up | C18: 6. Iceberg smoke test. Create a table, insert, read back, list snapshots, and see data and metadata objects in the RustFS console. | D18: Task | E18: Not started
A19: SU-S1-07 | B19: S1 Platform bring-up | C19: 7. S3A smoke test. Write and read Parquet at an s3a path and compare with Iceberg's own file I/O. | D19: Task | E19: Not started
A20: SU-S1-08 | B20: S1 Platform bring-up | C20: 8. JDBC smoke test. Read a 1M-row test table with several partitions and watch the connections in Postgres. | D20: Task | E20: Not started
A21: SU-S1-09 | B21: S1 Platform bring-up | C21: 9. History server shows a finished application with its event log in the bucket. | D21: Task | E21: Not started
A22: SU-S1-10 | B22: S1 Platform bring-up | C22: 10. End-to-end hello pipeline: Postgres -> landing Parquet -> Iceberg bronze -> query. Run twice; the second run must be idempotent. | D22: Task | E22: Not started
A23: S2 RustFS smoke tests
A24: SU-S2-01 | B24: S2 RustFS smoke tests | C24: Write and read a Parquet file through both S3A and Iceberg file I/O. | D24: Experiment | E24: Not started
A25: SU-S2-02 | B25: S2 RustFS smoke tests | C25: Write an object larger than the multipart threshold. | D25: Experiment | E25: Not started
A26: SU-S2-03 | B26: S2 RustFS smoke tests | C26: List a prefix with 10k+ objects (note time and pagination). | D26: Experiment | E26: Not started
A27: SU-S2-04 | B27: S2 RustFS smoke tests | C27: Delete many objects (cleanup and orphan removal path). | D27: Experiment | E27: Not started
A28: SU-S2-05 | B28: S2 RustFS smoke tests | C28: Two Spark applications writing at once. | D28: Experiment | E28: Not started
A29: SU-S2-06 | B29: S2 RustFS smoke tests | C29: Read an Iceberg table's metadata tables. | D29: Experiment | E29: Not started
A30: SU-S2-07 | B30: S2 RustFS smoke tests | C30: Kill RustFS during a write, restart, verify table and objects. | D30: Experiment | E30: Not started
A31: SU-S2-08 | B31: S2 RustFS smoke tests | C31: Smoke-test results recorded; every difference from AWS S3 behavior noted. | D31: Exit check | E31: Not started
A32: S3 Dataset acquisition
A33: SU-S3-01 | B33: S3 Dataset acquisition | C33: Create a Kaggle account and accept the Instacart competition rules so the files unlock. | D33: Task | E33: Not started
A34: SU-S3-02 | B34: S3 Dataset acquisition | C34: Read the dataset terms (learning use only; keep your copy out of shared repositories). | D34: Task | E34: Not started
A35: SU-S3-03 | B35: S3 Dataset acquisition | C35: Download all files and record checksums. | D35: Task | E35: Not started
A36: SU-S3-04 | B36: S3 Dataset acquisition | C36: Store an immutable copy under landing/raw_dump. | D36: Task | E36: Not started
A37: SU-S3-05 | B37: S3 Dataset acquisition | C37: Record file sizes and plain line counts (your first reconciliation numbers). | D37: Task | E37: Not started
A38: SU-S3-06 | B38: S3 Dataset acquisition | C38: Raw files stored untouched, with checksums and line counts written down. | D38: Exit check | E38: Not started
A39: S4 Helpers
A40: SU-S4-01 | B40: S4 Helpers | C40: Dataset loader (stage as text, type, constrain, log violations to the defect register). | D40: Task | E40: Not started
A41: SU-S4-02 | B41: S4 Helpers | C41: Timeline builder (rebuild timestamps from gaps, hours, weekdays; report inconsistencies). | D41: Task | E41: Not started
A42: SU-S4-03 | B42: S4 Helpers | C42: Enricher (users, stores, price book, totals, payments, lifecycle). | D42: Task | E42: Not started
A43: SU-S4-04 | B43: S4 Helpers | C43: Sampler / upscaler (reproducible S, M, L tiers). | D43: Task | E43: Not started
A44: SU-S4-05 | B44: S4 Helpers | C44: Lifecycle replayer (change simulator with adjustable speed and late-change probability). | D44: Task | E44: Not started
A45: SU-S4-06 | B45: S4 Helpers | C45: Clickstream generator (continuous and bulk JSON sessions to landing). | D45: Task | E45: Not started
A46: SU-S4-07 | B46: S4 Helpers | C46: Session factory (master, driver host, catalog, S3 settings, event-log location, per-experiment overrides). | D46: Task | E46: Not started
A47: SU-S4-08 | B47: S4 Helpers | C47: Timer and job labeler. | D47: Task | E47: Not started
A48: SU-S4-09 | B48: S4 Helpers | C48: No-op executor (forces full execution without a write). | D48: Task | E48: Not started
A49: SU-S4-10 | B49: S4 Helpers | C49: Plan reporter (scan filters, join types, exchange counts). | D49: Task | E49: Not started
A50: SU-S4-11 | B50: S4 Helpers | C50: Iceberg inspector (files, sizes, snapshots, manifests from metadata tables). | D50: Task | E50: Not started
A51: SU-S4-12 | B51: S4 Helpers | C51: Reconciler (counts and checksums across source, bronze, silver, gold). | D51: Task | E51: Not started
A52: S5 Conventions
A53: SU-S5-01 | B53: S5 Conventions | C53: Keep the Defect register, Experiment log and Decision log current (tabs in this workbook). | D53: Task | E53: Not started
A54: SU-S5-02 | B54: S5 Conventions | C54: Decide run id and extract id conventions carried into every layer. | D54: Task | E54: Not started
A55: SU-S5-03 | B55: S5 Conventions | C55: Decide namespaces (bronze, silver, gold, quarantine) and the landing path convention (source / table / extract date / extract id). | D55: Task | E55: Not started
A56: SU-S5-04 | B56: S5 Conventions | C56: Fix random seeds for every generator so any tier can be rebuilt identically. | D56: Task | E56: Not started
A57: SU-S5-05 | B57: S5 Conventions | C57: Decide time-zone policy: store UTC, document the assumed local zone for the rebuilt timeline. | D57: Task | E57: Not started
A58: SU-S5-06 | B58: S5 Conventions | C58: All gates decided, all 10 bring-up steps verified, helpers usable, conventions written down. | D58: Exit check | E58: Not started

Sheet P1_ETL
A1: Project 1: Lakehouse medallion ETL
A2: Source: 01-lakehouse-medallion-etl.md. Edit only the yellow cells: Status (dropdown), Started, Completed, Evidence / notes.
A3: Progress | B3: =IFERROR(COUNTIF($E$6:$E$600,"Done")/(COUNTA($E$6:$E$600)-COUNTIF($E$6:$E$600,"Skipped")),0) -> 0 | C3: =COUNTIF($E$6:$E$600,"Done")&" of "&(COUNTA($E$6:$E$600)-COUNTIF($E$6:$E$600,"Skipped"))&" items done | In progress: "&COUNTIF($E$6:$E$600,"In progress")&" | Blocked: "&COUNTIF($E$6:$E$600,"Blocked")&" | Skipped: "&COUNTIF($E$6:$E$600,"Skipped") -> 0 of 113 items done | In progress: 0 | Blocked: 0 | Skipped: 0
A5: ID | B5: Milestone | C5: Task | D5: Type | E5: Status | F5: Started | G5: Completed | H5: Evidence / notes
A6: M0 Load, profile, enrich
A7: P1-M0-01 | B7: M0 Load, profile, enrich | C7: Keep an untouched copy of the raw files in landing/raw_dump (everything must be reproducible from it). | D7: Task | E7: Not started
A8: P1-M0-02 | B8: M0 Load, profile, enrich | C8: Create a staging schema with every column as text; load all files; note rows per second for each loading method. | D8: Task | E8: Not started
A9: P1-M0-03 | B9: M0 Load, profile, enrich | C9: Fix CSV parsing of product names (commas, quotes): naive reader vs quoted-CSV reader; log the broken-row count as a defect. | D9: Task | E9: Not started
A10: P1-M0-04 | B10: M0 Load, profile, enrich | C10: Type the data in a second step; capture every row that fails to cast. | D10: Task | E10: Not started
A11: P1-M0-05 | B11: M0 Load, profile, enrich | C11: Profile every table: row count, null rate, distinct counts, min/max, text lengths, top values, duplicate rate on candidate keys. | D11: Task | E11: Not started
A12: P1-M0-06 | B12: M0 Load, profile, enrich | C12: Profile relationships (orphan counts per candidate foreign key, cardinality), distributions (basket size, orders per user, product frequency, hour/weekday) and temporal fields (days_since_prior_order, spike at the cap, nulls by order_number). | D12: Task | E12: Not started
A13: P1-M0-07 | B13: M0 Load, profile, enrich | C13: Union prior and train lines into one table with a source-file column; decide and record how test-set orders (no lines) are represented. | D13: Task | E13: Not started
A14: P1-M0-08 | B14: M0 Load, profile, enrich | C14: Add constraints in stages (PKs on small tables and orders, composite PK on lines, FKs lines->orders/products, products->aisles/departments); fill the constraint status table with violation counts. | D14: Task | E14: Not started
A15: P1-M0-09 | B15: M0 Load, profile, enrich | C15: Verify the reordered flag against each user's history; interpret mismatches. | D15: Task | E15: Not started
A16: P1-M0-10 | B16: M0 Load, profile, enrich | C16: Build the rebuilt timeline (start date, first order, capped gaps, weekday mismatch rules); output timestamp and quality flag; report the weekday-fit rate. | D16: Task | E16: Not started
A17: P1-M0-11 | B17: M0 Load, profile, enrich | C17: Generate synthetic tables in dependency order: users, stores, price book, totals, payments, lifecycle, erasures, campaign calendar; test each with its validity rules. | D17: Task | E17: Not started
A18: P1-M0-12 | B18: M0 Load, profile, enrich | C18: Add updated_at and is_deleted, keys and FK indexes; deliberately skip one useful index (for example on the order timestamp). | D18: Task | E18: Not started
... A25: P1-M0-19 | B25: M0 Load, profile, enrich | C25: Defect register covers every issue in README section 3.3; constraint table complete; timeline report written; S and M row counts match the files. | D25: Exit check | E25: Not started
A26: M1 Full extraction
A27: P1-M1-01 | B27: M1 Full extraction | C27: Choose the snapshot-consistency approach per table (shared repeatable-read snapshot, quiet window, or accept and reconcile). | D27: Task | E27: Not started
A28: P1-M1-02 | B28: M1 Full extraction | C28: Choose a partitioning strategy per table (id ranges, hash, month, surrogate key); get bounds from a min/max query just before the run. | D28: Task | E28: Not started
A29: P1-M1-03 | B29: M1 Full extraction | C29: Measure rows per partition before the full run (large baskets make equal id ranges unequal). | D29: Task | E29: Not started
A30: P1-M1-04 | B30: M1 Full extraction | C30: Run the extract at a modest partition count, then scale up. | D30: Task | E30: Not started
A31: P1-M1-05 | B31: M1 Full extraction | C31: Land to a temporary location with the path convention, then publish a manifest last (table, extract id, rows, bytes, partitions, timestamps, snapshot id). | D31: Task | E31: Not started
A32: P1-M1-06 | B32: M1 Full extraction | C32: Validate row counts and a column checksum against Postgres. | D32: Task | E32: Not started
A33: P1-M1-07 | B33: M1 Full extraction | C33: Partition count sweep: 1, 4, 8, 16, 32 (time, Postgres connections, slowest task). | D33: Experiment | E33: Not started
A34: P1-M1-08 | B34: M1 Full extraction | C34: fetchsize sweep: small / default / large (executor memory, round trips). | D34: Experiment | E34: Not started
A35: P1-M1-09 | B35: M1 Full extraction | C35: Table option vs query with a subquery (what Postgres actually executes). | D35: Experiment | E35: Not started
A36: P1-M1-10 | B36: M1 Full extraction | C36: Landing format and compression: Parquet / CSV / JSON x snappy / zstd / none. | D36: Experiment | E36: Not started
A37: P1-M1-11 | B37: M1 Full extraction | C37: Output file size: many small vs few large files (later scan cost on RustFS). | D37: Experiment | E37: Not started
A38: P1-M1-12 | B38: M1 Full extraction | C38: Partition on the unindexed timestamp and observe the effect of the missing index. | D38: Experiment | E38: Not started
A39: P1-M1-13 | B39: M1 Full extraction | C39: All tables extracted with matching counts and checksums; manifest per extract; partition choices justified with evidence. | D39: Exit check | E39: Not started
A40: M2 Incremental extraction
A41: P1-M2-01 | B41: M2 Incremental extraction | C41: Start the lifecycle replayer so Postgres changes continuously. | D41: Task | E41: Not started
A42: P1-M2-02 | B42: M2 Incremental extraction | C42: Choose an extraction strategy per table (watermark on updated_at, monotonic key, change-log polling, snapshot diff) and justify each. | D42: Task | E42: Not started
A43: P1-M2-03 | B43: M2 Incremental extraction | C43: Build the control table: run id, lower/upper bound, status, row counts, start/finish times. | D43: Task | E43: Not started
A44: P1-M2-04 | B44: M2 Incremental extraction | C44: Measure real update lateness and set the overlap window from data. | D44: Task | E44: Not started
A45: P1-M2-05 | B45: M2 Incremental extraction | C45: Extract the window, land with run id, deduplicate on key and latest change. | D45: Task | E45: Not started
A46: P1-M2-06 | B46: M2 Incremental extraction | C46: Implement delete detection (soft-delete flag, tombstones in the change log, periodic full key reconciliation). | D46: Task | E46: Not started
A47: P1-M2-07 | B47: M2 Incremental extraction | C47: Prove idempotency: re-run the same window; fail a run midway and recover on the next run. | D47: Task | E47: Not started
A48: P1-M2-08 | B48: M2 Incremental extraction | C48: Reconcile counts and key sets between source and landing at intervals. | D48: Task | E48: Not started
A49: P1-M2-09 | B49: M2 Incremental extraction | C49: Compare strategies: watermark vs change-log polling vs snapshot diff (cost, missed changes). | D49: Experiment | E49: Not started
A50: P1-M2-10 | B50: M2 Incremental extraction | C50: Compare delete detection: flag, tombstone, reconciliation, flag + reconciliation. | D50: Experiment | E50: Not started
A51: P1-M2-11 | B51: M2 Incremental extraction | C51: A day of replayed changes arrives complete; no missed late updates; hard deletes detected within the documented lag. | D51: Exit check | E51: Not started
A52: M3 Bronze
A53: P1-M3-01 | B53: M3 Bronze | C53: Define the bronze contract: raw as received plus lineage columns (run id, extract id, source system, ingested time, source file, operation). | D53: Task | E53: Not started
A54: P1-M3-02 | B54: M3 Bronze | C54: Create one bronze table per source table (snapshot and incremental loads together). | D54: Task | E54: Not started
A55: P1-M3-03 | B55: M3 Bronze | C55: Decide typed vs all-string bronze and record it. | D55: Task | E55: Not started
A56: P1-M3-04 | B56: M3 Bronze | C56: Choose table properties: format version, file format, compression, target file size. | D56: Task | E56: Not started
A57: P1-M3-05 | B57: M3 Bronze | C57: Choose partitioning for the lines table; predict file counts, then verify with the metadata tables. | D57: Task | E57: Not started
A58: P1-M3-06 | B58: M3 Bronze | C58: Load from landing; load clickstream with an explicit schema, corrupt-record capture and the planned schema drift handled. | D58: Task | E58: Not started
A59: P1-M3-07 | B59: M3 Bronze | C59: After every write inspect snapshots, files, manifests, partitions and compare with the RustFS objects. | D59: Task | E59: Not started
A60: P1-M3-08 | B60: M3 Bronze | C60: Sanity-check: counts match landing manifests; trace sample rows back to source. | D60: Task | E60: Not started
A61: P1-M3-09 | B61: M3 Bronze | C61: Lines partitioning: month of order date / day of load / bucket on order id / department / unpartitioned sorted. | D61: Experiment | E61: Not started
A62: P1-M3-10 | B62: M3 Bronze | C62: Two compression codecs and two target file sizes. | D62: Experiment | E62: Not started
A63: P1-M3-11 | B63: M3 Bronze | C63: Typed vs all-string bronze; one table vs two tables for snapshots and increments. | D63: Experiment | E63: Not started
A64: P1-M3-12 | B64: M3 Bronze | C64: All bronze tables reconciled with landing; each partition choice evaluated with file counts and sizes; lineage complete. | D64: Exit check | E64: Not started
A65: M4 Silver
A66: P1-M4-01 | B66: M4 Silver | C66: Order lines: dedupe on order + product; validate add_to_cart_order is gap-free; flag orders without lines; join the price valid at order time. | D66: Task | E66: Not started
A67: P1-M4-02 | B67: M4 Silver | C67: Orders: validate user history (contiguous, unique order numbers); keep raw eval_set; apply timeline; flag cancelled; quarantine impossible lifecycles. | D67: Task | E67: Not started
A68: P1-M4-03 | B68: M4 Silver | C68: Products and taxonomy: conform three levels; explicit unknown for the placeholder aisle/department; normalize names. | D68: Task | E68: Not started
A69: P1-M4-04 | B69: M4 Silver | C69: Users SCD2: valid_from / valid_to / is_current for membership tier; prove with as-of queries. | D69: Task | E69: Not started
A70: P1-M4-05 | B70: M4 Silver | C70: Prices: effective-dated; detect overlaps and gaps; resolve promotions by precedence. | D70: Task | E70: Not started
A71: P1-M4-06 | B71: M4 Silver | C71: Payments: reconcile against priced lines + fees + tip; classify mismatches. | D71: Task | E71: Not started
A72: P1-M4-07 | B72: M4 Silver | C72: Reorder flag: rebuild from history; compare with the source flag; quarantine or flag disagreements. | D72: Task | E72: Not started
A73: P1-M4-08 | B73: M4 Silver | C73: Clickstream: dedupe on event id; handle late events; map sessions to orders; quarantine malformed events. | D73: Task | E73: Not started
A74: P1-M4-09 | B74: M4 Silver | C74: MERGE design for every current-state table: match key, newer-wins rule, collapse the batch first, delete handling. | D74: Task | E74: Not started
A75: P1-M4-10 | B75: M4 Silver | C75: Prove MERGE idempotency (apply the same batch twice). | D75: Task | E75: Not started
A76: P1-M4-11 | B76: M4 Silver | C76: Build quarantine tables with a reason-code catalog and rule version; decide reject / flag / count per rule. | D76: Task | E76: Not started
A77: P1-M4-12 | B77: M4 Silver | C77: Build and run the data-quality rule catalog (completeness, validity, uniqueness, referential, consistency, timeliness); store metrics per run. | D77: Task | E77: Not started
... A83: P1-M4-18 | B83: M4 Silver | C83: Row accounting balances (bronze = silver + quarantined + deduplicated); SCD2 as-of queries correct; merges idempotent. | D83: Exit check | E83: Not started
A84: M5 Gold
A85: P1-M5-01 | B85: M5 Gold | C85: Write grain, inputs, pitfalls and invariants for every mart before building. | D85: Task | E85: Not started
A86: P1-M5-02 | B86: M5 Gold | C86: Mart: reorder rate by product, aisle, department (exclude orders with no lines; define denominators). | D86: Task | E86: Not started
A87: P1-M5-03 | B87: M5 Gold | C87: Mart: basket analytics (items per order, department mix, add-to-cart position vs reorder). | D87: Task | E87: Not started
A88: P1-M5-04 | B88: M5 Gold | C88: Mart: order cadence (gap distribution with capped gaps as censored; hour by weekday). | D88: Task | E88: Not started
A89: P1-M5-05 | B89: M5 Gold | C89: Mart: user 360 (recency, frequency, monetary; favorites; department vector). | D89: Task | E89: Not started
A90: P1-M5-06 | B90: M5 Gold | C90: Mart: cohorts (first-order month by order number; incomplete months). | D90: Task | E90: Not started
A91: P1-M5-07 | B91: M5 Gold | C91: Mart: top-N products per department per month (deterministic ties). | D91: Task | E91: Not started
A92: P1-M5-08 | B92: M5 Gold | C92: Mart: product co-occurrence (decide pruning and basket caps; see Project 2). | D92: Task | E92: Not started
A93: P1-M5-09 | B93: M5 Gold | C93: Mart: next-basket features (as-of date, last N orders, no leakage). | D93: Task | E93: Not started
A94: P1-M5-10 | B94: M5 Gold | C94: Choose a refresh strategy per mart: full rebuild, partition overwrite, MERGE, delete + insert. | D94: Task | E94: Not started
A95: P1-M5-11 | B95: M5 Gold | C95: Run each refresh strategy twice and diff the outputs (idempotency). | D95: Experiment | E95: Not started
A96: P1-M5-12 | B96: M5 Gold | C96: Layout: partition by date vs department; bucket by user; pre-aggregate; cache a shared input; sort order. | D96: Experiment | E96: Not started
A97: P1-M5-13 | B97: M5 Gold | C97: Every mart has a documented grain and passing invariants; three refresh strategies tried on one mart; reruns identical. | D97: Exit check | E97: Not started
A98: M6 Evolution and WAP
A99: P1-M6-01 | B99: M6 Evolution and WAP | C99: Time travel by snapshot id and by timestamp; compare a gold number before and after a load. | D99: Task | E99: Not started
A100: P1-M6-02 | B100: M6 Evolution and WAP | C100: Load wrong data on purpose (for example a mis-versioned price book), detect it, roll back; record what was rolled back. | D100: Task | E100: Not started
A101: P1-M6-03 | B101: M6 Evolution and WAP | C101: Schema evolution matrix: add nullable column, add with default meaning, rename, drop, widen a type, reorder; check old and new readers. | D101: Task | E101: Not started
A102: P1-M6-04 | B102: M6 Evolution and WAP | C102: Partition evolution on lines (monthly -> daily): confirm old files unchanged; read plans across both specs; decide on rewrite. | D102: Task | E102: Not started
A103: P1-M6-05 | B103: M6 Evolution and WAP | C103: Branch and tag: stage a load on a branch, run the DQ suite, publish only if checks pass; tag month-end snapshots. | D103: Task | E103: Not started
A104: P1-M6-06 | B104: M6 Evolution and WAP | C104: Define snapshot and tag retention policy. | D104: Task | E104: Not started
A105: P1-M6-07 | B105: M6 Evolution and WAP | C105: A rollback restored a clean state; every evolution type has a recorded outcome; a failing check blocked a publish. | D105: Exit check | E105: Not started
A106: M7 Maintenance
A107: P1-M7-01 | B107: M7 Maintenance | C107: Baseline: file counts and sizes, manifest, snapshot and delete-file counts, scan time of three reference queries. | D107: Task | E107: Not started
A108: P1-M7-02 | B108: M7 Maintenance | C108: Create the mess (tiny appends, many merges producing delete files, many snapshots); re-measure. | D108: Task | E108: Not started
A109: P1-M7-03 | B109: M7 Maintenance | C109: Compaction: bin-pack vs sort vs z-order; target size; minimum input files. | D109: Experiment | E109: Not started
A110: P1-M7-04 | B110: M7 Maintenance | C110: Manifest rewrite: effect on planning time. | D110: Experiment | E110: Not started
A111: P1-M7-05 | B111: M7 Maintenance | C111: Delete-file compaction after merge-on-read. | D111: Experiment | E111: Not started
A112: P1-M7-06 | B112: M7 Maintenance | C112: Snapshot expiry: retention age and minimum snapshots kept (time travel lost vs storage returned). | D112: Experiment | E112: Not started
...

Sheet P2_Joins
A1: Project 2: Joins, shuffles and skew
A2: Source: 02-joins-shuffle-skew.md. Edit only the yellow cells: Status (dropdown), Started, Completed, Evidence / notes.
A3: Progress | B3: =IFERROR(COUNTIF($E$6:$E$600,"Done")/(COUNTA($E$6:$E$600)-COUNTIF($E$6:$E$600,"Skipped")),0) -> 0 | C3: =COUNTIF($E$6:$E$600,"Done")&" of "&(COUNTA($E$6:$E$600)-COUNTIF($E$6:$E$600,"Skipped"))&" items done | In progress: "&COUNTIF($E$6:$E$600,"In progress")&" | Blocked: "&COUNTIF($E$6:$E$600,"Blocked")&" | Skipped: "&COUNTIF($E$6:$E$600,"Skipped") -> 0 of 91 items done | In progress: 0 | Blocked: 0 | Skipped: 0
A5: ID | B5: Milestone | C5: Task | D5: Type | E5: Status | F5: Started | G5: Completed | H5: Evidence / notes
A6: M0 Test bed and baselines
A7: P2-M0-01 | B7: M0 Test bed and baselines | C7: Freeze the data version: record Iceberg snapshot ids of lines, orders, products, aisles, departments, users, stores, price book, payments, events. | D7: Task | E7: Not started
A8: P2-M0-02 | B8: M0 Test bed and baselines | C8: Define benchmark queries J1-J8 (reorder rate by dept/aisle; orders by store/day; revenue per store/day; top-10 products per user; co-occurrence; price range join; payments reconciliation; lake x Postgres). | D8: Task | E8: Not started
A9: P2-M0-03 | B9: M0 Test bed and baselines | C9: Profile keys: share of rows held by top 1/10/100 keys (product, aisle, department, store, user, hour/weekday, basket size). | D9: Task | E9: Not started
A10: P2-M0-04 | B10: M0 Test bed and baselines | C10: Build table variants: lines partitioned by month; lines and orders bucketed on order id (several bucket counts); compacted copies. | D10: Task | E10: Not started
A11: P2-M0-05 | B11: M0 Test bed and baselines | C11: Record baselines: run J1-J8 with defaults twice; log time, shuffle bytes, spill, tasks, plan fingerprint. | D11: Task | E11: Not started
A12: P2-M0-06 | B12: M0 Test bed and baselines | C12: Every query has a baseline and plan; key-skew table exists; variants compacted. | D12: Exit check | E12: Not started
A13: M1 Reading baseline plans
A14: P2-M1-01 | B14: M1 Reading baseline plans | C14: Annotate J1-J4 plans: scan, pushed filters, join type, exchange, sort, partial/final aggregate. | D14: Task | E14: Not started
A15: P2-M1-02 | B15: M1 Reading baseline plans | C15: Predict join types and reasons before checking the plan. | D15: Task | E15: Not started
A16: P2-M1-03 | B16: M1 Reading baseline plans | C16: Force sort-merge (disable auto-broadcast and AQE); count exchanges and sorts; compare time. | D16: Task | E16: Not started
A17: P2-M1-04 | B17: M1 Reading baseline plans | C17: Re-enable AQE; find runtime changes in the final plan. | D17: Task | E17: Not started
A18: P2-M1-05 | B18: M1 Reading baseline plans | C18: Note how Iceberg scans appear and which filters are pushed. | D18: Task | E18: Not started
A19: P2-M1-06 | B19: M1 Reading baseline plans | C19: At least 80% of join-type predictions correct; mismatches explained. | D19: Exit check | E19: Not started
A20: M2 Join strategies by hint
A21: P2-M2-01 | B21: M2 Join strategies by hint | C21: Force broadcast, sort-merge and shuffle-hash on product/aisle/department joins; compare. | D21: Task | E21: Not started
A22: P2-M2-02 | B22: M2 Join strategies by hint | C22: Find the largest broadcastable table given driver memory and broadcast timeout. | D22: Task | E22: Not started
A23: P2-M2-03 | B23: M2 Join strategies by hint | C23: Compare shuffle-hash vs sort-merge where the build side fits (time, memory per task, spill). | D23: Task | E23: Not started
A24: P2-M2-04 | B24: M2 Join strategies by hint | C24: Try the nested-loop hint on tiny inputs only. | D24: Task | E24: Not started
A25: P2-M2-05 | B25: M2 Join strategies by hint | C25: Broadcast side sizes: 50k, 1M, 5M rows. | D25: Experiment | E25: Not started
A26: P2-M2-06 | B26: M2 Join strategies by hint | C26: Auto-broadcast threshold: disabled / 10 MB / 100 MB. | D26: Experiment | E26: Not started
A27: P2-M2-07 | B27: M2 Join strategies by hint | C27: Swap the build side by table order or hint. | D27: Experiment | E27: Not started
A28: P2-M2-08 | B28: M2 Join strategies by hint | C28: Best strategy per query with its margin over the default. | D28: Exit check | E28: Not started
A29: M3 Federated joins
A30: P2-M3-01 | B30: M3 Federated joins | C30: Run J8 (lake lines x Postgres products and price book); read what was pushed vs pulled. | D30: Task | E30: Not started
A31: P2-M3-02 | B31: M3 Federated joins | C31: Run it twice and confirm Postgres is hit again each time. | D31: Task | E31: Not started
A32: P2-M3-03 | B32: M3 Federated joins | C32: Cached JDBC read. | D32: Experiment | E32: Not started
A33: P2-M3-04 | B33: M3 Federated joins | C33: Broadcast the JDBC read. | D33: Experiment | E33: Not started
A34: P2-M3-05 | B34: M3 Federated joins | C34: Snapshot the Postgres tables into Iceberg first. | D34: Experiment | E34: Not started
A35: P2-M3-06 | B35: M3 Federated joins | C35: Join inside Postgres via a pushed-down subquery. | D35: Experiment | E35: Not started
A36: P2-M3-07 | B36: M3 Federated joins | C36: Observe Postgres connections, queries, load, locks; test selective vs unselective cases. | D36: Task | E36: Not started
A37: P2-M3-08 | B37: M3 Federated joins | C37: Break-even rule written (queries per hour, data volume) for each approach. | D37: Exit check | E37: Not started
A38: M4 Diagnosing skew
A39: P2-M4-01 | B39: M4 Diagnosing skew | C39: Aggregate and join on product, department, aisle, store, hour and the bulk buyer; record min/median/max task time, slowest-task shuffle read vs median, spill. | D39: Task | E39: Not started
A40: P2-M4-02 | B40: M4 Diagnosing skew | C40: Show skew in four places: a join, a window by user, a MERGE with a hot source key, uneven JDBC partitions. | D40: Task | E40: Not started
A41: P2-M4-03 | B41: M4 Diagnosing skew | C41: Contrast high-cardinality skew (hot product) with low-cardinality skew (21 departments): idle partitions. | D41: Task | E41: Not started
A42: P2-M4-04 | B42: M4 Diagnosing skew | C42: Write the skew checklist (UI signals + key-profile signals). | D42: Task | E42: Not started
A43: P2-M4-05 | B43: M4 Diagnosing skew | C43: Cause identified from the UI alone in all four cases. | D43: Exit check | E43: Not started
A44: M5 Skew-fix ladder
A45: P2-M5-01 | B45: M5 Skew-fix ladder | C45: AQE skew handling: lower thresholds, find skew markers, note where it does not apply. | D45: Experiment | E45: Not started
A46: P2-M5-02 | B46: M5 Skew-fix ladder | C46: Salting with factors 4, 8, 32 (joins; two-phase aggregations). | D46: Experiment | E46: Not started
A47: P2-M5-03 | B47: M5 Skew-fix ladder | C47: Hot-key isolation: broadcast top K keys, shuffle the rest, union. | D47: Experiment | E47: Not started
A48: P2-M5-04 | B48: M5 Skew-fix ladder | C48: Pre-aggregation to product-and-day grain. | D48: Experiment | E48: Not started
A49: P2-M5-05 | B49: M5 Skew-fix ladder | C49: Denormalize the dimension into the lines table. | D49: Experiment | E49: Not started
A50: P2-M5-06 | B50: M5 Skew-fix ladder | C50: Repeat the best fixes for an aggregation and for a MERGE. | D50: Task | E50: Not started
A51: P2-M5-07 | B51: M5 Skew-fix ladder | C51: Build the comparison table: time, max/median ratio, shuffle bytes, spill, complexity. | D51: Task | E51: Not started
A52: P2-M5-08 | B52: M5 Skew-fix ladder | C52: Chosen fix for a join, an aggregation and a MERGE, each with evidence. | D52: Exit check | E52: Not started
A53: M6 Pair explosion
A54: P2-M6-01 | B54: M6 Pair explosion | C54: Predict the pair count from the basket-size distribution. | D54: Task | E54: Not started
A55: P2-M6-02 | B55: M6 Pair explosion | C55: Check on a small sample; measure at M if feasible. | D55: Task | E55: Not started
A56: P2-M6-03 | B56: M6 Pair explosion | C56: Explain why a few huge baskets dominate pair counts, shuffle size and spill. | D56: Task | E56: Not started
A57: P2-M6-04 | B57: M6 Pair explosion | C57: Cap or sample huge baskets. | D57: Experiment | E57: Not started
A58: P2-M6-05 | B58: M6 Pair explosion | C58: Prune to frequent products before pairing. | D58: Experiment | E58: Not started
A59: P2-M6-06 | B59: M6 Pair explosion | C59: Canonical pair order (halve the work). | D59: Experiment | E59: Not started
A60: P2-M6-07 | B60: M6 Pair explosion | C60: Partial pre-aggregation per pair. | D60: Experiment | E60: Not started
A61: P2-M6-08 | B61: M6 Pair explosion | C61: Split by department and combine. | D61: Experiment | E61: Not started
A62: P2-M6-09 | B62: M6 Pair explosion | C62: Mark each fix: changes the answer vs changes only the plan. | D62: Task | E62: Not started
A63: P2-M6-10 | B63: M6 Pair explosion | C63: Same top pairs from at least two methods, with documented cost and accuracy difference. | D63: Exit check | E63: Not started
A64: M7 Range joins
A65: P2-M7-01 | B65: M7 Range joins | C65: Price each line from the effective-dated price book; record the join type. | D65: Task | E65: Not started
A66: P2-M7-02 | B66: M7 Range joins | C66: Expanded daily price table + equi-join. | D66: Experiment | E66: Not started
A67: P2-M7-03 | B67: M7 Range joins | C67: Time-bucket (weeks) join then filter. | D67: Experiment | E67: Not started
A68: P2-M7-04 | B68: M7 Range joins | C68: Sorted as-of lookup. | D68: Experiment | E68: Not started
A69: P2-M7-05 | B69: M7 Range joins | C69: Broadcast the price book. | D69: Experiment | E69: Not started
A70: P2-M7-06 | B70: M7 Range joins | C70: Repeat with the campaign calendar. | D70: Task | E70: Not started
A71: P2-M7-07 | B71: M7 Range joins | C71: Test at M, then L; verify identical results on a sample. | D71: Task | E71: Not started
A72: P2-M7-08 | B72: M7 Range joins | C72: One approach runs in reasonable time at L with verified identical results. | D72: Exit check | E72: Not started
A73: M8 Partition sizing and writes
A74: P2-M8-01 | B74: M8 Partition sizing and writes | C74: AQE off: sweep shuffle partitions 8 to 1000 on J1, J3, J4 and plot time. | D74: Task | E74: Not started
A75: P2-M8-02 | B75: M8 Partition sizing and writes | C75: AQE on: vary advisory size 16 MB to 256 MB; find coalesced reads in the plan. | D75: Task | E75: Not started
A76: P2-M8-03 | B76: M8 Partition sizing and writes | C76: Write distribution modes none / hash / range (shuffle cost, files per partition, file sizes). | D76: Experiment | E76: Not started
A77: P2-M8-04 | B77: M8 Partition sizing and writes | C77: Write down how shuffle partitions x distribution mode x table partitioning decide output file count; test it. | D77: Task | E77: Not started
A78: P2-M8-05 | B78: M8 Partition sizing and writes | C78: You can predict the file count of a write before running it. | D78: Exit check | E78: Not started
A79: M9 Storage-partitioned joins
A80: P2-M9-01 | B80: M9 Storage-partitioned joins | C80: Build orders and lines bucketed identically on order id (same bucket count). | D80: Task | E80: Not started
A81: P2-M9-02 | B81: M9 Storage-partitioned joins | C81: Enable the required Spark and Iceberg settings (check docs for your version). | D81: Task | E81: Not started
A82: P2-M9-03 | B82: M9 Storage-partitioned joins | C82: Confirm no exchange on either side; compare time with a regular join. | D82: Task | E82: Not started
A83: P2-M9-04 | B83: M9 Storage-partitioned joins | C83: Break it: different bucket counts. | D83: Experiment | E83: Not started
A84: P2-M9-05 | B84: M9 Storage-partitioned joins | C84: Break it: extra partition column. | D84: Experiment | E84: Not started
A85: P2-M9-06 | B85: M9 Storage-partitioned joins | C85: Break it: different join key. | D85: Experiment | E85: Not started
A86: P2-M9-07 | B86: M9 Storage-partitioned joins | C86: Break it: one side unbucketed. | D86: Experiment | E86: Not started
A87: P2-M9-08 | B87: M9 Storage-partitioned joins | C87: Compare with Hive-style bucketing. | D87: Experiment | E87: Not started
A88: P2-M9-09 | B88: M9 Storage-partitioned joins | C88: Recommend a bucket count; note the design-time cost. | D88: Task | E88: Not started
A89: P2-M9-10 | B89: M9 Storage-partitioned joins | C89: List of conditions under which the optimization applies. | D89: Exit check | E89: Not started
A90: M10 Memory pressure and spill
A91: P2-M10-01 | B91: M10 Memory pressure and spill | C91: Large sort / aggregation / merge with small executors and few partitions; record spill and GC. | D91: Task | E91: Not started
A92: P2-M10-02 | B92: M10 Memory pressure and spill | C92: Fix: more partitions. | D92: Experiment | E92: Not started
A93: P2-M10-03 | B93: M10 Memory pressure and spill | C93: Fix: fewer cores per executor. | D93: Experiment | E93: Not started
A94: P2-M10-04 | B94: M10 Memory pressure and spill | C94: Fix: larger execution memory share. | D94: Experiment | E94: Not started
A95: P2-M10-05 | B95: M10 Memory pressure and spill | C95: Fix: project early (narrower rows). | D95: Experiment | E95: Not started
A96: P2-M10-06 | B96: M10 Memory pressure and spill | C96: Repeat for a MERGE; compare copy-on-write and merge-on-read memory behavior. | D96: Task | E96: Not started
A97: P2-M10-07 | B97: M10 Memory pressure and spill | C97: Rank the fixes by effect per effort. | D97: Task | E97: Not started
A98: P2-M10-08 | B98: M10 Memory pressure and spill | C98: Each spill explained and matched to the fix that addressed it. | D98: Exit check | E98: Not started
A99: M11 Anti-pattern gallery
A100: P2-M11-01 | B100: M11 Anti-pattern gallery | C100: Non-equi joins and joins on expressions (for example a normalized product name). | D100: Task | E100: Not started
A101: P2-M11-02 | B101: M11 Anti-pattern gallery | C101: distinct before a join. | D101: Task | E101: Not started
...

Sheet P3_Planner
A1: Project 3: Catalyst and query planning
A2: Source: 03-catalyst-and-query-planning.md. Edit only the yellow cells: Status (dropdown), Started, Completed, Evidence / notes.
A3: Progress | B3: =IFERROR(COUNTIF($E$6:$E$600,"Done")/(COUNTA($E$6:$E$600)-COUNTIF($E$6:$E$600,"Skipped")),0) -> 0 | C3: =COUNTIF($E$6:$E$600,"Done")&" of "&(COUNTA($E$6:$E$600)-COUNTIF($E$6:$E$600,"Skipped"))&" items done | In progress: "&COUNTIF($E$6:$E$600,"In progress")&" | Blocked: "&COUNTIF($E$6:$E$600,"Blocked")&" | Skipped: "&COUNTIF($E$6:$E$600,"Skipped") -> 0 of 79 items done | In progress: 0 | Blocked: 0 | Skipped: 0
A5: ID | B5: Milestone | C5: Task | D5: Type | E5: Status | F5: Started | G5: Completed | H5: Evidence / notes
A6: M0 Variants and query suite
A7: P3-M0-01 | B7: M0 Variants and query suite | C7: Build lines/events variants: unsorted monthly-partitioned; sorted by product; z-ordered (department, hour); unpartitioned sorted; raw Parquet copy in landing. | D7: Task | E7: Not started
A8: P3-M0-02 | B8: M0 Variants and query suite | C8: Compact every variant to the same target file size. | D8: Task | E8: Not started
A9: P3-M0-03 | B9: M0 Variants and query suite | C9: Define Q1-Q12 (point lookup, low selectivity, date + hour, five-way join with selective dimension, bad join order, metadata-only aggregates, window by user, sampled pairs, price range join, JDBC filter + aggregate, UDF in filter, wide vs narrow select). | D9: Task | E9: Not started
A10: P3-M0-04 | B10: M0 Variants and query suite | C10: Record baselines: time, bytes read, files scanned, plan fingerprint. | D10: Task | E10: Not started
A11: P3-M0-05 | B11: M0 Variants and query suite | C11: All variants exist and are compacted; suite runs and is logged. | D11: Exit check | E11: Not started
A12: M1 Plan literacy
A13: P3-M1-01 | B13: M1 Plan literacy | C13: Predict Q1-Q4 plans (scan, pushed filters, joins, exchanges) before reading them. | D13: Task | E13: Not started
A14: P3-M1-02 | B14: M1 Plan literacy | C14: Read parsed, analyzed, optimized and physical plans; compare with predictions. | D14: Task | E14: Not started
A15: P3-M1-03 | B15: M1 Plan literacy | C15: Find constant folding, column pruning, predicate pushdown through a join, limit pushdown. | D15: Task | E15: Not started
A16: P3-M1-04 | B16: M1 Plan literacy | C16: Learn every scan-node field (pushed, read, remaining). | D16: Task | E16: Not started
A17: P3-M1-05 | B17: M1 Plan literacy | C17: Turn off one optimizer rule on a tiny sample; observe; restore. | D17: Task | E17: Not started
A18: P3-M1-06 | B18: M1 Plan literacy | C18: Compare how Iceberg, JDBC and raw Parquet scans look in plans. | D18: Task | E18: Not started
A19: P3-M1-07 | B19: M1 Plan literacy | C19: Learn plan formats: formatted, cost, codegen, SQL tab graph. | D19: Task | E19: Not started
A20: P3-M1-08 | B20: M1 Plan literacy | C20: At least 80% of plan-feature predictions correct. | D20: Exit check | E20: Not started
A21: M2 Iceberg pruning
A22: P3-M2-01 | B22: M2 Iceberg pruning | C22: Q1/Q3 on the partitioned variant: confirm a timestamp filter prunes without naming a partition column (hidden partitioning). | D22: Task | E22: Not started
A23: P3-M2-02 | B23: M2 Iceberg pruning | C23: Compare file-level skipping (min/max) across unsorted, sorted and z-ordered variants for equality and range filters. | D23: Task | E23: Not started
A24: P3-M2-03 | B24: M2 Iceberg pruning | C24: Prove files and bytes scanned vs total with the metadata tables. | D24: Task | E24: Not started
A25: P3-M2-04 | B25: M2 Iceberg pruning | C25: Compare planning vs execution time; build a many-manifest table to test. | D25: Task | E25: Not started
A26: P3-M2-05 | B26: M2 Iceberg pruning | C26: Q6: can count, min and max be answered from metadata in your versions? | D26: Task | E26: Not started
A27: P3-M2-06 | B27: M2 Iceberg pruning | C27: Q2: explain why pruning helps little for a low-selectivity filter. | D27: Task | E27: Not started
A28: P3-M2-07 | B28: M2 Iceberg pruning | C28: Partition transform: month / day / bucket / none. | D28: Experiment | E28: Not started
A29: P3-M2-08 | B29: M2 Iceberg pruning | C29: File size: small / target / large (planning time, RustFS requests). | D29: Experiment | E29: Not started
A30: P3-M2-09 | B30: M2 Iceberg pruning | C30: Filter shapes: equality, range, IN list, OR. | D30: Experiment | E30: Not started
A31: P3-M2-10 | B31: M2 Iceberg pruning | C31: For each query: files skipped, which metadata enabled it, how to improve it. | D31: Exit check | E31: Not started
A32: M3 Runtime filtering
A33: P3-M3-01 | B33: M3 Runtime filtering | C33: Q4 with a selective dimension filter; look for runtime partition pruning and bloom-filter runtime filters. | D33: Task | E33: Not started
A34: P3-M3-02 | B34: M3 Runtime filtering | C34: Toggle each runtime filter setting; record rows scanned and time. | D34: Experiment | E34: Not started
A35: P3-M3-03 | B35: M3 Runtime filtering | C35: Find when the filter is not inserted (non-selective, large build side, unsupported join, unpartitioned fact). | D35: Task | E35: Not started
A36: P3-M3-04 | B36: M3 Runtime filtering | C36: Compare with a manual rewrite (explicit filter on the fact table). | D36: Task | E36: Not started
A37: P3-M3-05 | B37: M3 Runtime filtering | C37: Conditions that trigger each runtime filter described for your tables. | D37: Exit check | E37: Not started
A38: M4 Statistics and cost-based planning
A39: P3-M4-01 | B39: M4 Statistics and cost-based planning | C39: Q5 with cost-based optimization off: record join order and time. | D39: Task | E39: Not started
A40: P3-M4-02 | B40: M4 Statistics and cost-based planning | C40: Collect table and column statistics; enable CBO and join reordering; re-run. | D40: Task | E40: Not started
A41: P3-M4-03 | B41: M4 Statistics and cost-based planning | C41: Read the cost plan; compare estimates with actuals; explain the worst misestimate. | D41: Task | E41: Not started
A42: P3-M4-04 | B42: M4 Statistics and cost-based planning | C42: Histograms on a skewed column (department). | D42: Experiment | E42: Not started
A43: P3-M4-05 | B43: M4 Statistics and cost-based planning | C43: Stale vs refreshed statistics after adding a day of data. | D43: Experiment | E43: Not started
A44: P3-M4-06 | B44: M4 Statistics and cost-based planning | C44: Find which statistics Iceberg and Spark actually use in your versions. | D44: Task | E44: Not started
A45: P3-M4-07 | B45: M4 Statistics and cost-based planning | C45: When CBO helped, when it hurt, and what upkeep it needs. | D45: Exit check | E45: Not started
A46: M5 JDBC pushdown
A47: P3-M5-01 | B47: M5 JDBC pushdown | C47: Equality or range filter on an indexed column: pushed? index used? | D47: Experiment | E47: Not started
A48: P3-M5-02 | B48: M5 JDBC pushdown | C48: Same filter on the unindexed timestamp: sequential scan cost at M. | D48: Experiment | E48: Not started
A49: P3-M5-03 | B49: M5 JDBC pushdown | C49: Aggregate over the table: pushed or pulled across? | D49: Experiment | E49: Not started
A50: P3-M5-04 | B50: M5 JDBC pushdown | C50: Limit and offset: pushed? ordering issues. | D50: Experiment | E50: Not started
A51: P3-M5-05 | B51: M5 JDBC pushdown | C51: Sampling: pushed? | D51: Experiment | E51: Not started
A52: P3-M5-06 | B52: M5 JDBC pushdown | C52: Filter with a Spark-only function or UDF: why pushdown fails. | D52: Experiment | E52: Not started
A53: P3-M5-07 | B53: M5 JDBC pushdown | C53: Cast on a filtered column: blocks index use? | D53: Experiment | E53: Not started
A54: P3-M5-08 | B54: M5 JDBC pushdown | C54: Partitioned read with explicit predicates: does each partition hit an index? | D54: Experiment | E54: Not started
A55: P3-M5-09 | B55: M5 JDBC pushdown | C55: Reading a view or arbitrary query: how aliasing changes planning. | D55: Experiment | E55: Not started
A56: P3-M5-10 | B56: M5 JDBC pushdown | C56: For each case capture three views: Spark plan, SQL text Postgres received, Postgres execution plan. | D56: Task | E56: Not started
A57: P3-M5-11 | B57: M5 JDBC pushdown | C57: Toggle each pushdown option; record rows transferred and time. | D57: Task | E57: Not started
A58: P3-M5-12 | B58: M5 JDBC pushdown | C58: Write the rule of thumb: logic in Postgres vs logic in Spark. | D58: Task | E58: Not started
A59: P3-M5-13 | B59: M5 JDBC pushdown | C59: Pushdown matrix complete with evidence for every row. | D59: Exit check | E59: Not started
A60: M6 AQE re-planning
A61: P3-M6-01 | B61: M6 AQE re-planning | C61: Build a query where one side looks large at plan time but small after filtering; compare initial vs final plan. | D61: Task | E61: Not started
A62: P3-M6-02 | B62: M6 AQE re-planning | C62: Record which AQE features fired (coalesce, local reader, skew, join switch). | D62: Task | E62: Not started
A63: P3-M6-03 | B63: M6 AQE re-planning | C63: Disable each AQE feature in turn and measure. | D63: Experiment | E63: Not started
A64: P3-M6-04 | B64: M6 AQE re-planning | C64: Find a case where AQE does not help. | D64: Task | E64: Not started
A65: P3-M6-05 | B65: M6 AQE re-planning | C65: You can predict which AQE features fire for a given query. | D65: Exit check | E65: Not started
A66: M7 Whole-stage codegen
A67: P3-M7-01 | B67: M7 Whole-stage codegen | C67: Find the codegen stage markers in a filter, project and aggregate. | D67: Task | E67: Not started
A68: P3-M7-02 | B68: M7 Whole-stage codegen | C68: Disable whole-stage codegen on a CPU-bound query and compare. | D68: Experiment | E68: Not started
A69: P3-M7-03 | B69: M7 Whole-stage codegen | C69: 200+ column table: does codegen fall back? What does the plan show? | D69: Experiment | E69: Not started
A70: P3-M7-04 | B70: M7 Whole-stage codegen | C70: Note operators that break codegen stages. | D70: Task | E70: Not started
A71: P3-M7-05 | B71: M7 Whole-stage codegen | C71: Speed difference and fallback rule explained. | D71: Exit check | E71: Not started
A72: M8 Optimizer blockers
A73: P3-M8-01 | B73: M8 Optimizer blockers | C73: Python UDF inside a filter (Q11) -> rewrite with built-ins. | D73: Experiment | E73: Not started
A74: P3-M8-02 | B74: M8 Optimizer blockers | C74: Expression on the filtered column (casts, formatting) -> sargable predicate. | D74: Experiment | E74: Not started
A75: P3-M8-03 | B75: M8 Optimizer blockers | C75: OR across partition and non-partition columns -> split and union. | D75: Experiment | E75: Not started
A76: P3-M8-04 | B76: M8 Optimizer blockers | C76: Non-deterministic function in a filter -> move after the join. | D76: Experiment | E76: Not started
A77: P3-M8-05 | B77: M8 Optimizer blockers | C77: Cached table hides the scan -> cache only narrowed data. | D77: Experiment | E77: Not started
A78: P3-M8-06 | B78: M8 Optimizer blockers | C78: Wide select into a wide join -> project early. | D78: Experiment | E78: Not started
A79: P3-M8-07 | B79: M8 Optimizer blockers | C79: Many small files or manifests -> compact; rewrite manifests. | D79: Experiment | E79: Not started
A80: P3-M8-08 | B80: M8 Optimizer blockers | C80: Self-join of lines for co-occurrence -> prune to frequent products and cap baskets. | D80: Experiment | E80: Not started
A81: P3-M8-09 | B81: M8 Optimizer blockers | C81: Filter on an unindexed Postgres column -> add index or move work to the lake. | D81: Experiment | E81: Not started
A82: P3-M8-10 | B82: M8 Optimizer blockers | C82: Join on a normalized product name -> normalize once in silver. | D82: Experiment | E82: Not started
A83: P3-M8-11 | B83: M8 Optimizer blockers | C83: Range join to the price book -> expand to daily rows and equi-join. | D83: Experiment | E83: Not started
A84: P3-M8-12 | B84: M8 Optimizer blockers | C84: Every pitfall has a measured before and after. | D84: Exit check | E84: Not started
A85: M9 Layout optimization
A86: P3-M9-01 | B86: M9 Layout optimization | C86: Sort order: product vs order date vs z-order for Q1, Q2, Q3, Q12. | D86: Experiment | E86: Not started
A87: P3-M9-02 | B87: M9 Layout optimization | C87: Parquet settings: row-group size, page size, compression, dictionary encoding; column bloom filters for a high-cardinality lookup. | D87: Experiment | E87: Not started
A88: P3-M9-03 | B88: M9 Layout optimization | C88: Format: Iceberg/Parquet vs ORC vs raw landing Parquet. | D88: Experiment | E88: Not started
A89: P3-M9-04 | B89: M9 Layout optimization | C89: File size 32 MB vs 128 MB vs 512 MB (RustFS requests, planning time). | D89: Experiment | E89: Not started
A90: P3-M9-05 | B90: M9 Layout optimization | C90: Compaction strategy: query speed per rewrite cost. | D90: Experiment | E90: Not started
A91: P3-M9-06 | B91: M9 Layout optimization | C91: Capture RustFS request count and throughput per layout. | D91: Task | E91: Not started
A92: P3-M9-07 | B92: M9 Layout optimization | C92: Layout recommended for point lookup, range scan and full scan, with numbers. | D92: Exit check | E92: Not started
A93: M10 Synthesis
A94: P3-M10-01 | B94: M10 Synthesis | C94: Write the one-page planner cheat sheet (reading each scan type, first checks, top ten blockers, top five layout rules) with experiment ids. | D94: Task | E94: Not started
A95: P3-M10-02 | B95: M10 Synthesis | C95: You can read a plan and predict runtime behavior; every pruning and pushdown claim has evidence. | D95: Exit check | E95: Not started

Sheet P4_Perf
A1: Project 4: Executors, memory and I/O performance
A2: Source: 04-executors-memory-io-performance.md. Edit only the yellow cells: Status (dropdown), Started, Completed, Evidence / notes.
A3: Progress | B3: =IFERROR(COUNTIF($E$6:$E$600,"Done")/(COUNTA($E$6:$E$600)-COUNTIF($E$6:$E$600,"Skipped")),0) -> 0 | C3: =COUNTIF($E$6:$E$600,"Done")&" of "&(COUNTA($E$6:$E$600)-COUNTIF($E$6:$E$600,"Skipped"))&" items done | In progress: "&COUNTIF($E$6:$E$600,"In progress")&" | Blocked: "&COUNTIF($E$6:$E$600,"Blocked")&" | Skipped: "&COUNTIF($E$6:$E$600,"Skipped") -> 0 of 91 items done | In progress: 0 | Blocked: 0 | Skipped: 0
A5: ID | B5: Milestone | C5: Task | D5: Type | E5: Status | F5: Started | G5: Completed | H5: Evidence / notes
A6: M0 Workloads and baselines
A7: P4-M0-01 | B7: M0 Workloads and baselines | C7: Define W1-W6: scan-heavy, shuffle-heavy, CPU-heavy (per-line score), memory-heavy (cache + wide aggregation), write-heavy (layout rewrite), mixed user-feature build. | D7: Task | E7: Not started
A8: P4-M0-02 | B8: M0 Workloads and baselines | C8: Instrument every run with Spark UI, Iceberg metadata, RustFS, Postgres and host CPU/memory/disk. | D8: Task | E8: Not started
A9: P4-M0-03 | B9: M0 Workloads and baselines | C9: Record baselines with the default layout, twice each. | D9: Task | E9: Not started
A10: P4-M0-04 | B10: M0 Workloads and baselines | C10: Classify each workload by apparent bottleneck (to test later). | D10: Task | E10: Not started
A11: P4-M0-05 | B11: M0 Workloads and baselines | C11: Each workload has a stable baseline (under 10% variation) and a first bottleneck guess. | D11: Exit check | E11: Not started
A12: M1 Topology and strong scaling
A13: P4-M1-01 | B13: M1 Topology and strong scaling | C13: Layout: 4 executors x (2 cores, 1 GB). | D13: Experiment | E13: Not started
A14: P4-M1-02 | B14: M1 Topology and strong scaling | C14: Layout: 8 executors x (1 core, 1 GB). | D14: Experiment | E14: Not started
A15: P4-M1-03 | B15: M1 Topology and strong scaling | C15: Layout: 4 executors x (2 cores, 2 GB). | D15: Experiment | E15: Not started
A16: P4-M1-04 | B16: M1 Topology and strong scaling | C16: Layout: 8 executors x (1 core, 512 MB). | D16: Experiment | E16: Not started
A17: P4-M1-05 | B17: M1 Topology and strong scaling | C17: Run W1-W4 on each layout; record time, spill, GC. | D17: Task | E17: Not started
A18: P4-M1-06 | B18: M1 Topology and strong scaling | C18: Strong scaling with 1, 2, 4, 8 total cores; compute speedup and efficiency; find where it flattens. | D18: Task | E18: Not started
A19: P4-M1-07 | B19: M1 Topology and strong scaling | C19: Diagnose the flat part: CPU-bound, storage-bound, source-bound or shuffle-bound. | D19: Task | E19: Not started
A20: P4-M1-08 | B20: M1 Topology and strong scaling | C20: Compare best layout for shuffle-heavy vs scan-heavy; note memory per task. | D20: Task | E20: Not started
A21: P4-M1-09 | B21: M1 Topology and strong scaling | C21: Scaling curve for each workload and a named bottleneck. | D21: Exit check | E21: Not started
A22: M2 Memory model
A23: P4-M2-01 | B23: M2 Memory model | C23: Read the Executors tab: storage memory, execution memory, GC time per task. | D23: Task | E23: Not started
A24: P4-M2-02 | B24: M2 Memory model | C24: Run W4; record cached fraction, spill and GC share. | D24: Task | E24: Not started
A25: P4-M2-03 | B25: M2 Memory model | C25: spark.memory.fraction: 0.4 / 0.6 / 0.8. | D25: Experiment | E25: Not started
A26: P4-M2-04 | B26: M2 Memory model | C26: spark.memory.storageFraction: 0.2 / 0.5 / 0.8. | D26: Experiment | E26: Not started
A27: P4-M2-05 | B27: M2 Memory model | C27: Off-heap memory: off vs on with a fixed size. | D27: Experiment | E27: Not started
A28: P4-M2-06 | B28: M2 Memory model | C28: GC algorithm via executor Java options: default vs parallel. | D28: Experiment | E28: Not started
A29: P4-M2-07 | B29: M2 Memory model | C29: Executor memory: 512m / 1g / 2g. | D29: Experiment | E29: Not started
A30: P4-M2-08 | B30: M2 Memory model | C30: Cause an out-of-memory failure on purpose; learn its signature in the error and UI. | D30: Task | E30: Not started
A31: P4-M2-09 | B31: M2 Memory model | C31: Note that memory overhead is not enforced in standalone; record the implication for YARN/Kubernetes. | D31: Task | E31: Not started
A32: P4-M2-10 | B32: M2 Memory model | C32: From task metrics you can say whether memory, GC or spill is the issue and what to change. | D32: Exit check | E32: Not started
A33: M3 Serialization and RDD
A34: P4-M3-01 | B34: M3 Serialization and RDD | C34: Same aggregation: group-by-key vs reduce-by-key vs DataFrame (shuffle bytes, time). | D34: Experiment | E34: Not started
A35: P4-M3-02 | B35: M3 Serialization and RDD | C35: Switch the serializer and explain why DataFrames barely change. | D35: Experiment | E35: Not started
A36: P4-M3-03 | B36: M3 Serialization and RDD | C36: Persistence levels on an RDD and a DataFrame cache. | D36: Experiment | E36: Not started
A37: P4-M3-04 | B37: M3 Serialization and RDD | C37: Shuffle compression codecs: lz4 / zstd / snappy on W2. | D37: Experiment | E37: Not started
A38: P4-M3-05 | B38: M3 Serialization and RDD | C38: Shuffle buffer settings. | D38: Experiment | E38: Not started
A39: P4-M3-06 | B39: M3 Serialization and RDD | C39: Rules for when RDD tricks help and when to stay with DataFrames. | D39: Exit check | E39: Not started
A40: M4 Python UDF ladder
A41: P4-M4-01 | B41: M4 Python UDF ladder | C41: Choose two per-row computations: math-heavy reorder-propensity score and product-name normalization + tokenization. | D41: Task | E41: Not started
A42: P4-M4-02 | B42: M4 Python UDF ladder | C42: Rung 1: built-in functions. | D42: Experiment | E42: Not started
A43: P4-M4-03 | B43: M4 Python UDF ladder | C43: Rung 2: SQL expressions and higher-order functions. | D43: Experiment | E43: Not started
A44: P4-M4-04 | B44: M4 Python UDF ladder | C44: Rung 3: row-at-a-time Python UDF. | D44: Experiment | E44: Not started
A45: P4-M4-05 | B45: M4 Python UDF ladder | C45: Rung 4: Arrow-optimized Python UDF. | D45: Experiment | E45: Not started
A46: P4-M4-06 | B46: M4 Python UDF ladder | C46: Rung 5: pandas UDF. | D46: Experiment | E46: Not started
A47: P4-M4-07 | B47: M4 Python UDF ladder | C47: Rung 6: map-in-Arrow or map-in-pandas. | D47: Experiment | E47: Not started
A48: P4-M4-08 | B48: M4 Python UDF ladder | C48: Rung 7: RDD map. | D48: Experiment | E48: Not started
A49: P4-M4-09 | B49: M4 Python UDF ladder | C49: Sweep Arrow batch size, Python worker memory limit, Python worker reuse. | D49: Experiment | E49: Not started
A50: P4-M4-10 | B50: M4 Python UDF ladder | C50: Decompose time into JVM, serialization and Python where the UI allows. | D50: Task | E50: Not started
A51: P4-M4-11 | B51: M4 Python UDF ladder | C51: Hot-key trap: grouped pandas computation per user overloads one worker (bulk buyer); fix with window functions or salting + two-phase. | D51: Task | E51: Not started
A52: P4-M4-12 | B52: M4 Python UDF ladder | C52: Verify identical results across rungs within tolerance. | D52: Task | E52: Not started
A53: P4-M4-13 | B53: M4 Python UDF ladder | C53: For any new transformation you can say which rung to start from and why. | D53: Exit check | E53: Not started
A54: M5 Object-store tuning
A55: P4-M5-01 | B55: M5 Object-store tuning | C55: Baseline W1 and W5; record RustFS request counts and throughput for full scan, filtered scan and write. | D55: Task | E55: Not started
A56: P4-M5-02 | B56: M5 Object-store tuning | C56: S3A connection pool maximum. | D56: Experiment | E56: Not started
A57: P4-M5-03 | B57: M5 Object-store tuning | C57: S3A thread pool size. | D57: Experiment | E57: Not started
A58: P4-M5-04 | B58: M5 Object-store tuning | C58: S3A fast-upload buffering mode (disk / array / byte buffer). | D58: Experiment | E58: Not started
A59: P4-M5-05 | B59: M5 Object-store tuning | C59: S3A multipart size and threshold. | D59: Experiment | E59: Not started
A60: P4-M5-06 | B60: M5 Object-store tuning | C60: S3A block size and read-ahead. | D60: Experiment | E60: Not started
A61: P4-M5-07 | B61: M5 Object-store tuning | C61: Access-pattern hint (sequential / random / adaptive). | D61: Experiment | E61: Not started
A62: P4-M5-08 | B62: M5 Object-store tuning | C62: S3A vs Iceberg's own S3 file I/O for the same table. | D62: Experiment | E62: Not started
A63: P4-M5-09 | B63: M5 Object-store tuning | C63: File size study: throughput vs file size; find where more size stops helping. | D63: Experiment | E63: Not started
A64: P4-M5-10 | B64: M5 Object-store tuning | C64: Find the setting that governs Iceberg scan task size and sweep it. | D64: Task | E64: Not started
A65: P4-M5-11 | B65: M5 Object-store tuning | C65: Watch for retry storms and timeouts under load (RustFS logs). | D65: Task | E65: Not started
A66: P4-M5-12 | B66: M5 Object-store tuning | C66: Recommended storage settings and target file size, with evidence. | D66: Exit check | E66: Not started
A67: M6 JDBC concurrency
A68: P4-M6-01 | B68: M6 JDBC concurrency | C68: Read parallelism 1, 2, 4, 8, 16, 32: Postgres connections, CPU, latency, Spark time. | D68: Experiment | E68: Not started
A69: P4-M6-02 | B69: M6 JDBC concurrency | C69: Find the point where Postgres hurts or Spark stops improving. | D69: Task | E69: Not started
A70: P4-M6-03 | B70: M6 JDBC concurrency | C70: Explain how executors and cores bound connections and which Postgres limit applies. | D70: Task | E70: Not started
A71: P4-M6-04 | B71: M6 JDBC concurrency | C71: Fetch size and executor memory behavior. | D71: Experiment | E71: Not started
A72: P4-M6-05 | B72: M6 JDBC concurrency | C72: Write a gold aggregate back: batch size, batched-insert rewrite option, write parallelism (locks, WAL, indexes). | D72: Experiment | E72: Not started
A73: P4-M6-06 | B73: M6 JDBC concurrency | C73: Staging table + swap vs writing into the live table. | D73: Experiment | E73: Not started
A74: P4-M6-07 | B74: M6 JDBC concurrency | C74: Write the backpressure policy (max parallelism, quiet windows, read replica, or extract from the change log). | D74: Task | E74: Not started
A75: P4-M6-08 | B75: M6 JDBC concurrency | C75: Maximum safe parallelism per Postgres workload stated with reasons. | D75: Exit check | E75: Not started
A76: M7 Concurrent writers
A77: P4-M7-01 | B77: M7 Concurrent writers | C77: Two appends at once (retry counts, commit time). | D77: Experiment | E77: Not started
A78: P4-M7-02 | B78: M7 Concurrent writers | C78: Two merges touching the same files (error text). | D78: Experiment | E78: Not started
A79: P4-M7-03 | B79: M7 Concurrent writers | C79: Merge vs compaction (who loses and why). | D79: Experiment | E79: Not started
A80: P4-M7-04 | B80: M7 Concurrent writers | C80: Append during snapshot expiry. | D80: Experiment | E80: Not started
A81: P4-M7-05 | B81: M7 Concurrent writers | C81: Write during orphan removal. | D81: Experiment | E81: Not started
A82: P4-M7-06 | B82: M7 Concurrent writers | C82: Tune commit retries and isolation levels; compare serializable and snapshot isolation. | D82: Task | E82: Not started
A83: P4-M7-07 | B83: M7 Concurrent writers | C83: Verify a failed commit leaves no visible partial data; measure orphan files. | D83: Task | E83: Not started
A84: P4-M7-08 | B84: M7 Concurrent writers | C84: Write isolation rules: which jobs may run together and in what order. | D84: Task | E84: Not started
A85: P4-M7-09 | B85: M7 Concurrent writers | C85: Table of safe and unsafe job combinations with a scheduling rule. | D85: Exit check | E85: Not started
A86: M8 Scheduling and allocation
A87: P4-M8-01 | B87: M8 Scheduling and allocation | C87: Dynamic allocation with shuffle tracking; sweep idle timeout and bounds. | D87: Experiment | E87: Not started
A88: P4-M8-02 | B88: M8 Scheduling and allocation | C88: Two notebooks (two applications) concurrently: how standalone shares cores. | D88: Experiment | E88: Not started
A89: P4-M8-03 | B89: M8 Scheduling and allocation | C89: FIFO vs FAIR scheduling with pools from separate threads. | D89: Experiment | E89: Not started
A90: P4-M8-04 | B90: M8 Scheduling and allocation | C90: Data-locality wait sweep; does it matter with RustFS? | D90: Experiment | E90: Not started
A91: P4-M8-05 | B91: M8 Scheduling and allocation | C91: Fair-sharing configuration described with numbers. | D91: Exit check | E91: Not started
A92: M9 Resilience
A93: P4-M9-01 | B93: M9 Resilience | C93: Straggler + speculation (multiplier, quantile); check for extra files in an Iceberg write. | D93: Experiment | E93: Not started
A94: P4-M9-02 | B94: M9 Resilience | C94: Executor loss: kill a worker mid-job (task and stage retries, outcome, retry limits). | D94: Experiment | E94: Not started
A95: P4-M9-03 | B95: M9 Resilience | C95: Storage failure: stop RustFS mid-write (errors, retries, table state, leftover files). | D95: Experiment | E95: Not started
A96: P4-M9-04 | B96: M9 Resilience | C96: Source failure: stop Postgres mid-extract (errors, half-published extract?). | D96: Experiment | E96: Not started
A97: P4-M9-05 | B97: M9 Resilience | C97: Failure-based exclusion with a deterministically failing task. | D97: Experiment | E97: Not started
A98: P4-M9-06 | B98: M9 Resilience | C98: Bring services back; confirm workers re-register and the next run succeeds. | D98: Task | E98: Not started
A99: P4-M9-07 | B99: M9 Resilience | C99: Each failure has a recorded timeline and a runbook entry. | D99: Exit check | E99: Not started
A100: M10 Shuffle internals
A101: P4-M10-01 | B101: M10 Shuffle internals | C101: Shuffle buffer and in-flight fetch settings on a large shuffle. | D101: Experiment | E101: Not started
...

Sheet P5_Streaming
A1: Project 5: Streaming and CDC into Iceberg
A2: Source: 05-streaming-cdc-lakehouse.md. Edit only the yellow cells: Status (dropdown), Started, Completed, Evidence / notes.
A3: Progress | B3: =IFERROR(COUNTIF($E$6:$E$600,"Done")/(COUNTA($E$6:$E$600)-COUNTIF($E$6:$E$600,"Skipped")),0) -> 0 | C3: =COUNTIF($E$6:$E$600,"Done")&" of "&(COUNTA($E$6:$E$600)-COUNTIF($E$6:$E$600,"Skipped"))&" items done | In progress: "&COUNTIF($E$6:$E$600,"In progress")&" | Blocked: "&COUNTIF($E$6:$E$600,"Blocked")&" | Skipped: "&COUNTIF($E$6:$E$600,"Skipped") -> 0 of 77 items done | In progress: 0 | Blocked: 0 | Skipped: 0
A5: ID | B5: Milestone | C5: Task | D5: Type | E5: Status | F5: Started | G5: Completed | H5: Evidence / notes
A6: M0 Sources, speeds, SLOs
A7: P5-M0-01 | B7: M0 Sources, speeds, SLOs | C7: Clickstream producer around real baskets, with duplicates/replays, malformed lines, schema drift, out-of-order events and ~2% very late events. | D7: Task | E7: Not started
A8: P5-M0-02 | B8: M0 Sources, speeds, SLOs | C8: Write files safely (temporary name then rename); decide the object naming convention. | D8: Task | E8: Not started
A9: P5-M0-03 | B9: M0 Sources, speeds, SLOs | C9: Run the lifecycle replayer with an adjustable time-compression factor. | D9: Task | E9: Not started
A10: P5-M0-04 | B10: M0 Sources, speeds, SLOs | C10: Verify the change log is ordered and complete. | D10: Task | E10: Not started
A11: P5-M0-05 | B11: M0 Sources, speeds, SLOs | C11: Choose three speeds: low (below capacity), medium (near), high (above). | D11: Task | E11: Not started
A12: P5-M0-06 | B12: M0 Sources, speeds, SLOs | C12: Define service levels before building: freshness, completeness, duplicates, late-data tolerance. | D12: Task | E12: Not started
A13: P5-M0-07 | B13: M0 Sources, speeds, SLOs | C13: Prepare batch reference truth for windows, sessions and current state. | D13: Task | E13: Not started
A14: P5-M0-08 | B14: M0 Sources, speeds, SLOs | C14: Producers run at three speeds; change log verified; service levels written down. | D14: Exit check | E14: Not started
A15: M1 Clickstream to bronze
A16: P5-M1-01 | B16: M1 Clickstream to bronze | C16: File stream with an explicit schema and a files-per-trigger cap; decide how to treat corrupt lines and the drifted field. | D16: Task | E16: Not started
A17: P5-M1-02 | B17: M1 Clickstream to bronze | C17: Write to Iceberg bronze with the checkpoint stored in RustFS. | D17: Task | E17: Not started
A18: P5-M1-03 | B18: M1 Clickstream to bronze | C18: Inspect the checkpoint folder (offsets, commits, sources, metadata) and write down what each represents. | D18: Task | E18: Not started
A19: P5-M1-04 | B19: M1 Clickstream to bronze | C19: Triggers: fixed interval vs available-now vs once. | D19: Experiment | E19: Not started
A20: P5-M1-05 | B20: M1 Clickstream to bronze | C20: Prove exactly-once: restart several times (also mid-batch); compare bronze count with a batch read of the same objects. | D20: Task | E20: Not started
A21: P5-M1-06 | B21: M1 Clickstream to bronze | C21: Watch progress metrics: input rate, processing rate, batch id, duration breakdown. | D21: Task | E21: Not started
A22: P5-M1-07 | B22: M1 Clickstream to bronze | C22: Listing cost as the landing prefix grows; cleanup options (off / archive / delete). | D22: Experiment | E22: Not started
A23: P5-M1-08 | B23: M1 Clickstream to bronze | C23: Decide bronze partitioning (ingestion day, hour, none) and predict file counts. | D23: Task | E23: Not started
A24: P5-M1-09 | B24: M1 Clickstream to bronze | C24: Restarts never lose or duplicate; batch metrics understood; counts match batch reads. | D24: Exit check | E24: Not started
A25: M2 Small files and maintenance
A26: P5-M2-01 | B26: M2 Small files and maintenance | C26: After an hour at medium speed count data files and snapshots in bronze. | D26: Task | E26: Not started
A27: P5-M2-02 | B27: M2 Small files and maintenance | C27: Run compaction and snapshot expiry while the stream runs; record conflicts and retries. | D27: Experiment | E27: Not started
A28: P5-M2-03 | B28: M2 Small files and maintenance | C28: Sink options: fanout vs sorted write; target file size; distribution mode. | D28: Experiment | E28: Not started
A29: P5-M2-04 | B29: M2 Small files and maintenance | C29: Find the trigger interval that meets both freshness and file-count targets. | D29: Task | E29: Not started
A30: P5-M2-05 | B30: M2 Small files and maintenance | C30: Design the maintenance schedule (cadence, order, safe windows, margins relative to the checkpoint). | D30: Task | E30: Not started
A31: P5-M2-06 | B31: M2 Small files and maintenance | C31: Schedule runs while the stream is live with a recorded conflict count; bronze stays within file-count targets. | D31: Exit check | E31: Not started
A32: M3 Windowed aggregates
A33: P5-M3-01 | B33: M3 Windowed aggregates | C33: One-minute tumbling and five-minute sliding counts by event type with a ten-minute watermark. | D33: Task | E33: Not started
A34: P5-M3-02 | B34: M3 Windowed aggregates | C34: Find which output modes the Iceberg sink supports; route upserts through a batch-by-batch merge. | D34: Task | E34: Not started
A35: P5-M3-03 | B35: M3 Windowed aggregates | C35: Watermark 1 min / 10 min / 1 h: emission delay, dropped rows, state size. | D35: Experiment | E35: Not started
A36: P5-M3-04 | B36: M3 Windowed aggregates | C36: Reconcile dropped rows with the producer's known late events. | D36: Task | E36: Not started
A37: P5-M3-05 | B37: M3 Windowed aggregates | C37: Tumbling vs sliding state size. | D37: Experiment | E37: Not started
A38: P5-M3-06 | B38: M3 Windowed aggregates | C38: Compare the stream result with batch truth. | D38: Task | E38: Not started
A39: P5-M3-07 | B39: M3 Windowed aggregates | C39: Stream matches batch except rows beyond the watermark, and you can explain the difference exactly. | D39: Exit check | E39: Not started
A40: M4 Sessionization
A41: P5-M4-01 | B41: M4 Sessionization | C41: 30-minute-gap sessions per user into gold: events, cart adds, conversions, revenue, start, end. | D41: Task | E41: Not started
A42: P5-M4-02 | B42: M4 Sessionization | C42: Verify against a batch computation over the same period. | D42: Task | E42: Not started
A43: P5-M4-03 | B43: M4 Sessionization | C43: Watermark lengths vs state size and memory per batch. | D43: Experiment | E43: Not started
A44: P5-M4-04 | B44: M4 Sessionization | C44: Find the hot user's state partition in the metrics (the bulk buyer). | D44: Task | E44: Not started
A45: P5-M4-05 | B45: M4 Sessionization | C45: Session gap 10 / 30 / 60 minutes. | D45: Experiment | E45: Not started
A46: P5-M4-06 | B46: M4 Sessionization | C46: Stretch: arbitrary-state API (check PySpark availability); compare flexibility, cost, correctness. | D46: Task | E46: Not started
A47: P5-M4-07 | B47: M4 Sessionization | C47: Streamed sessions equal batch sessions on closed periods; state growth model understood. | D47: Exit check | E47: Not started
A48: M5 CDC apply
A49: P5-M5-01 | B49: M5 CDC apply | C49: Poll the change log in micro-batches using the last applied sequence as the position. | D49: Task | E49: Not started
A50: P5-M5-02 | B50: M5 CDC apply | C50: Collapse each batch to the latest change per key by sequence; separate inserts, updates, soft and hard deletes. | D50: Task | E50: Not started
A51: P5-M5-03 | B51: M5 CDC apply | C51: MERGE into silver with match key, sequence comparison (ignore older changes) and delete handling. | D51: Task | E51: Not started
A52: P5-M5-04 | B52: M5 CDC apply | C52: Make each batch idempotent; store the last applied batch or sequence atomically with the merge. | D52: Task | E52: Not started
A53: P5-M5-05 | B53: M5 CDC apply | C53: Disorder tests: shuffle changes within a batch, replay old batches, drop one batch and detect the gap. | D53: Experiment | E53: Not started
A54: P5-M5-06 | B54: M5 CDC apply | C54: Deletes: erasure requests (hard delete + anonymize) and cascade effects. | D54: Experiment | E54: Not started
A55: P5-M5-07 | B55: M5 CDC apply | C55: Apply with MERGE vs append-only changelog + latest-per-key view (cost, audit, storage). | D55: Experiment | E55: Not started
A56: P5-M5-08 | B56: M5 CDC apply | C56: Batch size small vs large (commit rate, conflict risk). | D56: Experiment | E56: Not started
A57: P5-M5-09 | B57: M5 CDC apply | C57: Copy-on-write vs merge-on-read for the CDC target. | D57: Experiment | E57: Not started
A58: P5-M5-10 | B58: M5 CDC apply | C58: Try incremental reads from an Iceberg table (streaming source, changelog view); document supported snapshot types. | D58: Task | E58: Not started
A59: P5-M5-11 | B59: M5 CDC apply | C59: Replaying, reordering and dropping batches never corrupts silver; final state equals the batch rebuild. | D59: Exit check | E59: Not started
A60: M6 Dedup and joins
A61: P5-M6-01 | B61: M6 Dedup and joins | C61: Dedup by event id: classic with watermark vs within-watermark (state size, replays). | D61: Experiment | E61: Not started
A62: P5-M6-02 | B62: M6 Dedup and joins | C62: Stream-static join against an updating silver dimension; prove whether updates become visible while the stream runs. | D62: Task | E62: Not started
A63: P5-M6-03 | B63: M6 Dedup and joins | C63: Stream-stream join: views -> cart adds -> purchases with watermarks on both sides and a time-range condition. | D63: Task | E63: Not started
A64: P5-M6-04 | B64: M6 Dedup and joins | C64: Outer join: when unmatched rows are emitted. | D64: Experiment | E64: Not started
A65: P5-M6-05 | B65: M6 Dedup and joins | C65: Break it: remove a watermark; observe the error or unbounded state. | D65: Task | E65: Not started
A66: P5-M6-06 | B66: M6 Dedup and joins | C66: Compare results with batch truth. | D66: Task | E66: Not started
A67: P5-M6-07 | B67: M6 Dedup and joins | C67: Each pattern has documented state size, latency and correctness. | D67: Exit check | E67: Not started
A68: M7 State and throughput tuning
A69: P5-M7-01 | B69: M7 State and throughput tuning | C69: Change shuffle partitions on an existing stateful checkpoint; record what happens and why. | D69: Task | E69: Not started
A70: P5-M7-02 | B70: M7 State and throughput tuning | C70: Default state store vs RocksDB for large state (memory, batch time, checkpoint size). | D70: Experiment | E70: Not started
A71: P5-M7-03 | B71: M7 State and throughput tuning | C71: Raise producer rate until processing falls behind; control backlog with files-per-trigger and trigger interval. | D71: Experiment | E71: Not started
A72: P5-M7-04 | B72: M7 State and throughput tuning | C72: Chart batch duration vs trigger interval from recent progress records. | D72: Task | E72: Not started
A73: P5-M7-05 | B73: M7 State and throughput tuning | C73: Find the maximum sustainable rate and the first bottleneck (CPU, RustFS, commits, state). | D73: Task | E73: Not started
A74: P5-M7-06 | B74: M7 State and throughput tuning | C74: Maximum sustainable rate per query and its first bottleneck known. | D74: Exit check | E74: Not started
A75: M8 Failure drills
A76: P5-M8-01 | B76: M8 Failure drills | C76: Kill a worker (executor loss, retries, no data loss). | D76: Experiment | E76: Not started
A77: P5-M8-02 | B77: M8 Failure drills | C77: Stop the notebook kernel / kill the driver (restart from checkpoint, exact resume). | D77: Experiment | E77: Not started
A78: P5-M8-03 | B78: M8 Failure drills | C78: Stop RustFS during a batch (error, retry, checkpoint and table state). | D78: Experiment | E78: Not started
A79: P5-M8-04 | B79: M8 Failure drills | C79: Stop Postgres during CDC polling (resume without gaps or duplicates). | D79: Experiment | E79: Not started
A80: P5-M8-05 | B80: M8 Failure drills | C80: Add a column to the sink table while running. | D80: Experiment | E80: Not started
A81: P5-M8-06 | B81: M8 Failure drills | C81: Change the aggregation key or output mode (which errors?). | D81: Experiment | E81: Not started
A82: P5-M8-07 | B82: M8 Failure drills | C82: Damage part of the checkpoint (what recovery is possible?). | D82: Experiment | E82: Not started
A83: P5-M8-08 | B83: M8 Failure drills | C83: Each drill outcome matches prediction or the surprise is documented. | D83: Exit check | E83: Not started
A84: M9 Latency and SLOs
A85: P5-M9-01 | B85: M9 Latency and SLOs | C85: Mark a test change in Postgres; track it in the change log, micro-batch, silver and gold. | D85: Task | E85: Not started
A86: P5-M9-02 | B86: M9 Latency and SLOs | C86: Break total latency into stages (poll, batch wait, processing, commit, visibility). | D86: Task | E86: Not started
A87: P5-M9-03 | B87: M9 Latency and SLOs | C87: Latency at low, medium and high rates. | D87: Experiment | E87: Not started
A88: P5-M9-04 | B88: M9 Latency and SLOs | C88: Write checks for each service level (freshness lag, counts vs batch truth, duplicates); confirm they fire when you break something. | D88: Task | E88: Not started
A89: P5-M9-05 | B89: M9 Latency and SLOs | C89: Decide alert thresholds. | D89: Task | E89: Not started
A90: P5-M9-06 | B90: M9 Latency and SLOs | C90: Freshness measured per stage; checks alert correctly. | D90: Exit check | E90: Not started
A91: M10 Synthesis
A92: P5-M10-01 | B92: M10 Synthesis | C92: Write the operating guide: topology, rates and limits, maintenance schedule, recovery steps, service levels and checks, monitoring. Link experiment ids. | D92: Task | E92: Not started
A93: P5-M10-02 | B93: M10 Synthesis | C93: Silver and gold from the stream equal the batch rebuild on closed periods; failures never corrupt data; freshness measured with working checks. | D93: Exit check | E93: Not started

Sheet Environment
A1: Environment and versions
A2: Record what you actually pinned. Do NOT store passwords or keys in this file.
A4: Item | B4: Suggested (from the guide) | C4: Chosen / pinned | D4: Date pinned | E4: Verified how | F4: Notes
A5: Spark version | B5: 4.x (see Gate A)
A6: Scala version | B6: 2.13
A7: Java version | B7: 17 or 21 (confirm in Spark docs)
A8: Hadoop version bundled with Spark | B8: from your Spark distribution
A9: Iceberg Spark runtime artifact and version | B9: must match Spark minor version
A10: S3 access bundle (hadoop-aws + AWS SDK, or Iceberg AWS bundle) | B10: versions must match Hadoop
A11: PostgreSQL version
A12: PostgreSQL JDBC driver version
A13: RustFS release tag | B13: pin a tag, not latest
A14: Catalog type | B14: JDBC on Postgres (recommended)
A15: Source database name
A16: Catalog database name | B16: separate from source
A17: Spark executor layout | B17: 4 x (2 cores, 1 GB) to start
A18: Default shuffle partitions chosen | B18: 16 to 32 for 8 cores (data dependent)
A19: Port: Spark master / master UI | B19: 7077 / 8080
A20: Port: application UI / history server | B20: 4040 / 18080
A21: Port: RustFS S3 API / console | B21: 9000 / 9001
A22: Port: PostgreSQL / Jupyter | B22: 5432 / 8888
A23: Where credentials are stored (do NOT write them here) | B23: e.g. a password manager or env file
A25: Dataset tiers built
A26: Tier | B26: Orders | C26: Order lines | D26: Lines per order | E26: Built on | F26: Random seed | G26: Notes
A27: Example (M, full data) | B27: 3421083 | C27: 33819106 | D27: =IFERROR(C27/B27,"") -> 9.8854971 | E27: 2026-11-02 | F27: 42 | G27: EXAMPLE - overwrite with your own build
A28: S | D28: =IFERROR(C28/B28,"") | G28: ~10% of users, all of their orders (about 340k orders, 3.4M lines)
A29: M | D29: =IFERROR(C29/B29,"") | G29: full dataset (3.42M orders, about 33.8M lines)
A30: L | D30: =IFERROR(C30/B30,"") | G30: full dataset replicated ~3 times (about 10M orders, 100M lines)

Sheet Experiments
A1: Experiment log
A2: One row per experiment. Write the prediction BEFORE you run it. Row 6 is an example; overwrite or delete it.
A5: Exp ID | B5: Date | C5: Project | D5: Milestone | E5: Prediction (before running) | F5: Setting changed | G5: Baseline | H5: Result (time / bytes / shuffle / spill) | I5: Spark UI evidence | J5: Iceberg / RustFS / Postgres evidence | K5: Conclusion | L5: Follow-up | M5: Prediction correct?
A6: E-EX | B6: 2026-11-02 | C6: P2 | D6: M5 Skew-fix ladder | E6: AQE skew join will cut the max task time by half on the product-id join | F6: skewJoin thresholds lowered to 32 MB | G6: max/median task ratio 14x, 212 s | H6: ratio 3x, 96 s, shuffle read 18 GB | I6: Stage 7 task table; SQL plan shows skew=true | J6: RustFS GET count unchanged; Postgres idle | K6: AQE helps the join; no effect on the skewed aggregation | L6: Try salting on the aggregation | M6: Partly

Sheet Defects
A1: Defect register
A2: Pre-filled with the Instacart issues to verify. Change Status to Confirmed / Handled / Not found as you profile. Row 6 is an example.
A5: ID | B5: Table | C5: Column(s) | D5: Description | E5: Rows affected | F5: Table rows | G5: % of rows | H5: Severity | I5: How detected | J5: Handling rule | K5: Layer handled | L5: Proving test | M5: Status
A6: D-EX | B6: orders | C6: days_since_prior_order | D6: Null for each user's first order | E6: 206209 | F6: 3421083 | G6: =IF(AND(ISNUMBER(E6),ISNUMBER(F6),F6>0),E6/F6,"") -> 0.060275942 | H6: Low | I6: Null rate by order_number | J6: Keep null; derive is_first_order | K6: Silver | L6: Assert nulls only where order_number = 1 | M6: Handled
A7: D-001 | B7: orders | C7: eval_set | D7: Test-set orders have no order lines at all | G7: =IF(AND(ISNUMBER(E7),ISNUMBER(F7),F7>0),E7/F7,"") | H7: Medium | I7: Anti-join of orders to both lines files | J7: Keep in orders, flag has_lines = false, exclude from basket metrics | K7: Silver | M7: To verify
A8: D-002 | B8: order_products | C8: order_id | D8: Lines are split across two files (prior and train) that must be unioned | G8: =IF(AND(ISNUMBER(E8),ISNUMBER(F8),F8>0),E8/F8,"") | H8: Medium | I8: File inventory and row counts per file | J8: Union with a source-file column | K8: Bronze | M8: To verify
A9: D-003 | B9: orders | C9: days_since_prior_order | D9: Null for each user's first order | G9: =IF(AND(ISNUMBER(E9),ISNUMBER(F9),F9>0),E9/F9,"") | H9: Low | I9: Null rate by order_number | J9: Keep null; derive is_first_order | K9: Silver | M9: To verify
A10: D-004 | B10: orders | C10: days_since_prior_order | D10: Values appear capped near 30 days (censored data) | G10: =IF(AND(ISNUMBER(E10),ISNUMBER(F10),F10>0),E10/F10,"") | H10: Medium | I10: Value histogram spike at the cap | J10: Treat the cap as 'at least 30'; document in cadence mart | K10: Gold | M10: To verify
A11: D-005 | B11: orders | C11: order_dow, order_hour_of_day | D11: No timestamps: only weekday, hour and gap since previous order | G11: =IF(AND(ISNUMBER(E11),ISNUMBER(F11),F11>0),E11/F11,"") | H11: High | I11: Schema review | J11: Rebuilt timeline with quality flag | K11: Source | M11: To verify
A12: D-006 | B12: products | C12: aisle_id, department_id | D12: Placeholder 'missing' aisle and department | G12: =IF(AND(ISNUMBER(E12),ISNUMBER(F12),F12>0),E12/F12,"") | H12: Medium | I12: Distinct taxonomy values | J12: Map to explicit 'unknown' | K12: Silver | M12: To verify
A13: D-007 | B13: products | C13: product_name | D13: Names contain commas and quotes that break naive CSV parsing | G13: =IF(AND(ISNUMBER(E13),ISNUMBER(F13),F13>0),E13/F13,"") | H13: Low | I13: Compare naive vs quoted-CSV row counts | J13: Use a quoted-CSV reader | K13: Landing | M13: To verify
A14: D-008 | B14: order_products | C14: order_id | D14: Long tail of very large baskets | G14: =IF(AND(ISNUMBER(E14),ISNUMBER(F14),F14>0),E14/F14,"") | H14: Low | I14: Basket-size distribution | J14: Cap or prune in co-occurrence work | K14: Gold | M14: To verify
A15: D-009 | B15: order_products | C15: reordered | D15: Possible disagreements between the reordered flag and user history | G15: =IF(AND(ISNUMBER(E15),ISNUMBER(F15),F15>0),E15/F15,"") | H15: Medium | I15: Rebuild flag from history and compare | J15: Quarantine or flag disagreements | K15: Silver | M15: To verify
A16: D-010 | B16: orders | C16: order_number | D16: User histories may not line up with order_number (gaps or duplicates) | G16: =IF(AND(ISNUMBER(E16),ISNUMBER(F16),F16>0),E16/F16,"") | H16: Medium | I16: Contiguity check per user | J16: Quarantine impossible histories | K16: Silver | M16: To verify
A17: D-011 | B17: (all) | C17: price, payment, store, user | D17: No prices, payments, stores or user attributes exist in the source | G17: =IF(AND(ISNUMBER(E17),ISNUMBER(F17),F17>0),E17/F17,"") | H17: High | I17: Schema review | J17: Generate synthetic tables with documented rules | K17: Source | M17: To verify
G18: =IF(AND(ISNUMBER(E18),ISNUMBER(F18),F18>0),E18/F18,"")
G19: =IF(AND(ISNUMBER(E19),ISNUMBER(F19),F19>0),E19/F19,"")
G20: =IF(AND(ISNUMBER(E20),ISNUMBER(F20),F20>0),E20/F20,"")
G21: =IF(AND(ISNUMBER(E21),ISNUMBER(F21),F21>0),E21/F21,"")
G22: =IF(AND(ISNUMBER(E22),ISNUMBER(F22),F22>0),E22/F22,"")
G23: =IF(AND(ISNUMBER(E23),ISNUMBER(F23),F23>0),E23/F23,"")
G24: =IF(AND(ISNUMBER(E24),ISNUMBER(F24),F24>0),E24/F24,"")
G25: =IF(AND(ISNUMBER(E25),ISNUMBER(F25),F25>0),E25/F25,"")
G26: =IF(AND(ISNUMBER(E26),ISNUMBER(F26),F26>0),E26/F26,"")
G27: =IF(AND(ISNUMBER(E27),ISNUMBER(F27),F27>0),E27/F27,"")
G28: =IF(AND(ISNUMBER(E28),ISNUMBER(F28),F28>0),E28/F28,"")
G29: =IF(AND(ISNUMBER(E29),ISNUMBER(F29),F29>0),E29/F29,"")
... G60: =IF(AND(ISNUMBER(E60),ISNUMBER(F60),F60>0),E60/F60,"")

Sheet Decisions
A1: Decision log
A2: Decisions you must make during the lab. Fill in Evidence (experiment IDs), Choice and Status. Row 6 is an example.
A5: ID | B5: Date | C5: Decision needed | D5: Options considered | E5: Evidence (experiment IDs) | F5: Choice | G5: Revisit if | H5: Status
A6: DEC-EX | B6: 2026-11-02 | C6: Bronze partitioning for lines | D6: month of order date / bucket on order id / unpartitioned sorted | E6: E-021, E-022 | F6: month of order date | G6: date filters stop dominating queries | H6: Decided
A7: DEC-001 | C7: Spark version vs Iceberg runtime (Gate A) | D7: Spark 4.2 if the runtime exists; else newest 4.x with a published Iceberg runtime | H7: Open
A8: DEC-002 | C8: Catalog (Gate D) | D8: Hadoop / JDBC on Postgres / standalone REST / RustFS built-in S3 Tables (preview) | H8: Open
A9: DEC-003 | C9: Jar delivery (Gate C) | D9: Baked into the image vs resolved at runtime | H9: Open
A10: DEC-004 | C10: S3 access path | D10: Hadoop S3A + AWS SDK bundle vs Iceberg's own S3 file I/O | H10: Open
A11: DEC-005 | C11: S tier sampling method | D11: By user (recommended) vs by order | H11: Open
A12: DEC-006 | C12: Postgres lines table design | D12: Single table vs partitioned by order date | H12: Open
A13: DEC-007 | C13: Handling of test-set orders | D13: Keep / flag / separate table | H13: Open
A14: DEC-008 | C14: JDBC partitioning for order_items | D14: Order-id ranges / hash / month / surrogate key | H14: Open
A15: DEC-009 | C15: Snapshot consistency for the full extract | D15: Shared repeatable-read snapshot / quiet window / accept and reconcile | H15: Open
A16: DEC-010 | C16: Incremental strategy per table | D16: Watermark / monotonic key / change-log polling / snapshot diff | H16: Open
A17: DEC-011 | C17: Bronze typing | D17: Typed vs all-string | H17: Open
A18: DEC-012 | C18: Bronze partitioning for lines | D18: Month / day of load / bucket on order id / department / unpartitioned sorted | H18: Open
... A20: DEC-014 | C20: Maintenance cadence and snapshot retention | D20: Per table type; balance time travel needs vs storage | H20: Open

Sheet Config_Cards
A1: Configuration cards
A2: One card per key setting. Defaults come from the configuration map; verify them in the Environment tab of the Spark UI. Fill the yellow cells after an experiment.
A5: Project | B5: Config | C5: Default (verify) | D5: What it controls | E5: Too low / too high | F5: How I observed it | G5: Value chosen and why | H5: Interacts with | I5: Learned?
A6: P1/P2 | B6: spark.sql.shuffle.partitions | C6: 200 | D6: Partitions after a shuffle (joins, aggregates) | I6: Not started
A7: P2/P3 | B7: spark.sql.adaptive.enabled | C7: true | D7: AQE master switch | I7: Not started
A8: P2 | B8: spark.sql.adaptive.advisoryPartitionSizeInBytes | C8: 64MB | D8: Target partition size after coalescing or skew split | I8: Not started
A9: P2 | B9: spark.sql.adaptive.skewJoin.enabled | C9: true | D9: Splits skewed partitions in sort-merge joins | I9: Not started
A10: P2 | B10: spark.sql.autoBroadcastJoinThreshold | C10: 10MB | D10: Auto-broadcast size limit (-1 disables) | I10: Not started
A11: P4 | B11: spark.executor.cores | C11: all worker cores (standalone) | D11: Cores per executor | I11: Not started
A12: P4 | B12: spark.executor.memory | C12: 1g | D12: Executor heap | I12: Not started
A13: P4 | B13: spark.cores.max | C13: unlimited | D13: Total cores an application may take | I13: Not started
A14: P2 | B14: spark.driver.memory | C14: 1g | D14: Driver heap (collect, broadcast build) | I14: Not started
A15: P4 | B15: spark.memory.fraction | C15: 0.6 | D15: Heap share for execution plus storage | I15: Not started
A16: P4 | B16: spark.memory.storageFraction | C16: 0.5 | D16: Part of that share protected for cache | I16: Not started
A17: P1 | B17: JDBC numPartitions | C17: unset | D17: Read/write parallelism and max concurrent connections | I17: Not started
... A38: All | B38: spark.eventLog.enabled / spark.eventLog.dir | C38: false | D38: Event logs for the history server (can point at a bucket) | I38: Not started
